{"name": "Galactic watches1255", "slug": "galactic", "total": 1255, "page": 29, "references": [{"slug": "w7133012-a800-164s-a14s-1", "url": "/breitling/galactic/w7133012-a800-164s-a14s-1", "collection": "Galactic watches1255", "title": "Breitling - W7133012/A800/164S/A14S.1Galactic 32 Sleek Edition Stainless Steel / Pearl / Rubber", "specs": {"Brand": "Breitling", "Family": "Galactic", "Reference": "W7133012/A800/164S/A14S.1", "Name": "Galactic 32 Sleek Edition Stainless Steel / Pearl / Rubber", "Movement": "Breitling caliber Caliber B71Hours, Minutes, Seconds | Date | Chronometer", "Produced": "2017", "Limited": "No", "Materials": "Tungsten, Stainless Steel", "Glass": "Sapphire", "Back": "Closed", "Shape": "Round", "Diameter": "32.00 mm", "Height": "10.95 mm", "Lug Width": "16.00 mm", "W/R": "100.00 m", "Color": "White", "Material": "Mother of Pearl", "Indexes": "Stick / Dot", "Hands": "Stick"}, "image_url": "https://cdn.watchbase.com/watch/lg/breitling/galactic/w7133012-a800-164s-8a.jpg"}, {"slug": "w7133012-bf63-208x-a14ba-1", "url": "/breitling/galactic/w7133012-bf63-208x-a14ba-1", "collection": "Galactic watches1255", "title": "Breitling - W7133012/BF63/208X/A14BA.1Galactic 32 Sleek Edition Stainless Steel / Trophy Black Diamond / Sahara", "specs": {"Brand": "Breitling", "Family": "Galactic", "Reference": "W7133012/BF63/208X/A14BA.1", "Name": "Galactic 32 Sleek Edition Stainless Steel / Trophy Black Diamond / Sahara", "Movement": "Breitling caliber Caliber B71Hours, Minutes, Seconds | Date | Chronometer", "Produced": "2017", "Limited": "No", "Materials": "Tungsten, Stainless Steel", "Glass": "Sapphire", "Back": "Closed", "Shape": "Round", "Diameter": "32.00 mm", "Height": "10.95 mm", "Lug Width": "16.00 mm", "W/R": "100.00 m", "Nickname": "Trophy", "Color": "Black", "Indexes": "Gem-Set Indexes", "Hands": "Stick"}, "image_url": "https://cdn.watchbase.com/watch/lg/breitling/galactic/w7133012-bf63-208x-5.jpg"}, {"slug": "w7133012-bf63-777p-a14ba-1", "url": "/breitling/galactic/w7133012-bf63-777p-a14ba-1", "collection": "Galactic watches1255", "title": "Breitling - W7133012/BF63/777P/A14BA.1Galactic 32 Sleek Edition Stainless Steel / Trophy Black Diamond / Croco", "specs": {"Brand": "Breitling", "Family": "Galactic", "Reference": "W7133012/BF63/777P/A14BA.1", "Name": "Galactic 32 Sleek Edition Stainless Steel / Trophy Black Diamond / Croco", "Movement": "Breitling caliber Caliber B71Hours, Minutes, Seconds | Date | Chronometer", "Produced": "2017", "Limited": "No", "Materials": "Tungsten, Stainless Steel", "Glass": "Sapphire", "Back": "Closed", "Shape": "Round", "Diameter": "32.00 mm", "Height": "10.95 mm", "Lug Width": "16.00 mm", "W/R": "100.00 m", "Nickname": "Trophy", "Color": "Black", "Indexes": "Gem-Set Indexes", "Hands": "Stick"}, "image_url": "https://cdn.watchbase.com/watch/lg/breitling/galactic/w7133012-bf63-777p-68.jpg"}, {"slug": "w7133012-c966-406x-a14ba-1", "url": "/breitling/galactic/w7133012-c966-406x-a14ba-1", "collection": "Galactic watches1255", "title": "Breitling - W7133012/C966/406X/A14BA.1Galactic 32 Sleek Edition Stainless Steel / Horizon Blue Diamond / Calf", "specs": {"Brand": "Breitling", "Family": "Galactic", "Reference": "W7133012/C966/406X/A14BA.1", "Name": "Galactic 32 Sleek Edition Stainless Steel / Horizon Blue Diamond / Calf", "Movement": "Breitling caliber Caliber B71Hours, Minutes, Seconds | Date | Chronometer", "Produced": "2017", "Limited": "No", "Materials": "Tungsten, Stainless Steel", "Glass": "Sapphire", "Back": "Closed", "Shape": "Round", "Diameter": "32.00 mm", "Height": "10.95 mm", "Lug Width": "16.00 mm", "W/R": "100.00 m", "Nickname": "Horizon", "Color": "Blue", "Indexes": "Gem-Set Indexes", "Hands": "Stick"}, "image_url": "https://cdn.watchbase.com/watch/lg/breitling/galactic/w7133012-c966-406x-af.jpg"}, {"slug": "w7133012-c966-778p-a14ba-1", "url": "/breitling/galactic/w7133012-c966-778p-a14ba-1", "collection": "Galactic watches1255", "title": "Breitling - W7133012/C966/778P/A14BA.1Galactic 32 Sleek Edition Stainless Steel / Horizon Blue Diamond / Croco", "specs": {"Brand": "Breitling", "Family": "Galactic", "Reference": "W7133012/C966/778P/A14BA.1", "Name": "Galactic 32 Sleek Edition Stainless Steel / Horizon Blue Diamond / Croco", "Movement": "Breitling caliber Caliber B71Hours, Minutes, Seconds | Date | Chronometer", "Produced": "2017", "Limited": "No", "Materials": "Tungsten, Stainless Steel", "Glass": "Sapphire", "Back": "Closed", "Shape": "Round", "Diameter": "32.00 mm", "Height": "10.95 mm", "Lug Width": "16.00 mm", "W/R": "100.00 m", "Nickname": "Horizon", "Color": "Blue", "Indexes": "Gem-Set Indexes", "Hands": "Stick"}, "image_url": "https://cdn.watchbase.com/watch/lg/breitling/galactic/w7133012-c966-778p-f3.jpg"}, {"slug": "w7133012-a801-212x-a14ba-1", "url": "/breitling/galactic/w7133012-a801-212x-a14ba-1", "collection": "Galactic watches1255", "title": "Breitling - W7133012/A801/212X/A14BA.1 Galactic 32 Sleek Edition Stainless Steel / Pearl Diamond / Sahara", "specs": {"Brand": "Breitling", "Family": "Galactic", "Reference": "W7133012/A801/212X/A14BA.1", "Name": "Galactic 32 Sleek Edition Stainless Steel / Pearl Diamond / Sahara", "Movement": "Breitling caliber Caliber B71 Hours, Minutes, Seconds | Date | Chronometer", "Produced": "2017", "Limited": "No", "Materials": "Tungsten, Stainless Steel", "Glass": "Sapphire", "Back": "Closed", "Shape": "Round", "Diameter": "32.00 mm", "Height": "10.95 mm", "Lug Width": "16.00 mm", "W/R": "100.00 m", "Color": "White", "Material": "Mother of Pearl", "Indexes": "Gem-Set Indexes", "Hands": "Stick"}, "image_url": "https://cdn.watchbase.com/watch/lg/breitling/galactic/w7133012-a801-212x-1d.jpg"}, {"slug": "a7133053-c951-406x-a14ba-1", "url": "/breitling/galactic/a7133053-c951-406x-a14ba-1", "collection": "Galactic watches1255", "title": "Breitling - A7133053/C951/406X/A14BA.1 Galactic 32 Sleek Edition Stainless Steel / Diamond / Horizon Blue / Calf", "specs": {"Brand": "Breitling", "Family": "Galactic", "Reference": "A7133053/C951/406X/A14BA.1", "Name": "Galactic 32 Sleek Edition Stainless Steel / Diamond / Horizon Blue / Calf", "Movement": "Breitling caliber Caliber B71 Hours, Minutes, Seconds | Date | Chronometer", "Produced": "2017", "Limited": "No", "Material": "Stainless Steel", "Glass": "Sapphire", "Back": "Closed", "Shape": "Round", "Diameter": "32.00 mm", "Height": "10.95 mm", "Lug Width": "16.00 mm", "W/R": "100.00 m", "Nickname": "Horizon", "Color": "Blue", "Indexes": "Stick / Dot", "Hands": "Stick"}, "image_url": "https://cdn.watchbase.com/watch/lg/breitling/galactic/a7133053-c951-406x-de.jpg"}, {"slug": "a7133053-c951-235x-a14ba-1", "url": "/breitling/galactic/a7133053-c951-235x-a14ba-1", "collection": "Galactic watches1255", "title": "Breitling - A7133053/C951/235X/A14BA.1 Galactic 32 Sleek Edition Stainless Steel / Diamond / Horizon Blue / Sahara", "specs": {"Brand": "Breitling", "Family": "Galactic", "Reference": "A7133053/C951/235X/A14BA.1", "Name": "Galactic 32 Sleek Edition Stainless Steel / Diamond / Horizon Blue / Sahara", "Movement": "Breitling caliber Caliber B71 Hours, Minutes, Seconds | Date | Chronometer", "Produced": "2017", "Limited": "No", "Material": "Stainless Steel", "Glass": "Sapphire", "Back": "Closed", "Shape": "Round", "Diameter": "32.00 mm", "Height": "10.95 mm", "Lug Width": "16.00 mm", "W/R": "100.00 m", "Nickname": "Horizon", "Color": "Blue", "Indexes": "Stick / Dot", "Hands": "Stick"}, "image_url": "https://cdn.watchbase.com/watch/lg/breitling/galactic/a7133053-c951-235x-3.jpg"}, {"slug": "a7133053-a800-208x-a14ba-1", "url": "/breitling/galactic/a7133053-a800-208x-a14ba-1", "collection": "Galactic watches1255", "title": "Breitling - A7133053/A800/208X/A14BA.1 Galactic 32 Sleek Edition Stainless Steel / Diamond / Pearl / Sahara", "specs": {"Brand": "Breitling", "Family": "Galactic", "Reference": "A7133053/A800/208X/A14BA.1", "Name": "Galactic 32 Sleek Edition Stainless Steel / Diamond / Pearl / Sahara", "Movement": "Breitling caliber Caliber B71 Hours, Minutes, Seconds | Date | Chronometer", "Produced": "2017", "Limited": "No", "Material": "Mother of Pearl", "Glass": "Sapphire", "Back": "Closed", "Shape": "Round", "Diameter": "32.00 mm", "Height": "10.95 mm", "Lug Width": "16.00 mm", "W/R": "100.00 m", "Color": "White", "Indexes": "Stick / Dot", "Hands": "Stick"}, "image_url": "https://cdn.watchbase.com/watch/lg/breitling/galactic/a7133053-a800-208x-c2.jpg"}, {"slug": "a7133053-a800-238x-a14ba-1", "url": "/breitling/galactic/a7133053-a800-238x-a14ba-1", "collection": "Galactic watches1255", "title": "Breitling - A7133053/A800/238X/A14BA.1 Galactic 32 Sleek Edition Stainless Steel / Diamond / Pearl / Sahara", "specs": {"Brand": "Breitling", "Family": "Galactic", "Reference": "A7133053/A800/238X/A14BA.1", "Name": "Galactic 32 Sleek Edition Stainless Steel / Diamond / Pearl / Sahara", "Movement": "Breitling caliber Caliber B71 Hours, Minutes, Seconds | Date | Chronometer", "Produced": "2017", "Limited": "No", "Material": "Mother of Pearl", "Glass": "Sapphire", "Back": "Closed", "Shape": "Round", "Diameter": "32.00 mm", "Height": "10.95 mm", "Lug Width": "16.00 mm", "W/R": "100.00 m", "Color": "White", "Indexes": "Stick / Dot", "Hands": "Stick"}, "image_url": "https://cdn.watchbase.com/watch/lg/breitling/galactic/a7133053-a800-238x-ef.jpg"}, {"slug": "a7133053-bf62-410x-a14ba-1", "url": "/breitling/galactic/a7133053-bf62-410x-a14ba-1", "collection": "Galactic watches1255", "title": "Breitling - A7133053/BF62/410X/A14BA.1 Galactic 32 Sleek Edition Stainless Steel / Diamond / Trophy Black / Calf", "specs": {"Brand": "Breitling", "Family": "Galactic", "Reference": "A7133053/BF62/410X/A14BA.1", "Name": "Galactic 32 Sleek Edition Stainless Steel / Diamond / Trophy Black / Calf", "Movement": "Breitling caliber Caliber B71 Hours, Minutes, Seconds | Date | Chronometer", "Produced": "2017", "Limited": "No", "Material": "Stainless Steel", "Glass": "Sapphire", "Back": "Closed", "Shape": "Round", "Diameter": "32.00 mm", "Height": "10.95 mm", "Lug Width": "16.00 mm", "W/R": "100.00 m", "Nickname": "Trophy", "Color": "Black", "Indexes": "Stick / Dot", "Hands": "Stick"}, "image_url": "https://cdn.watchbase.com/watch/lg/breitling/galactic/a7133053-bf62-410x-7.jpg"}, {"slug": "a7133053-bf62-235x-a14ba-1", "url": "/breitling/galactic/a7133053-bf62-235x-a14ba-1", "collection": "Galactic watches1255", "title": "Breitling - A7133053/BF62/235X/A14BA.1 Galactic 32 Sleek Edition Stainless Steel / Diamond / Trophy Black / Sahara", "specs": {"Brand": "Breitling", "Family": "Galactic", "Reference": "A7133053/BF62/235X/A14BA.1", "Name": "Galactic 32 Sleek Edition Stainless Steel / Diamond / Trophy Black / Sahara", "Movement": "Breitling caliber Caliber B71 Hours, Minutes, Seconds | Date | Chronometer", "Produced": "2017", "Limited": "No", "Material": "Stainless Steel", "Glass": "Sapphire", "Back": "Closed", "Shape": "Round", "Diameter": "32.00 mm", "Height": "10.95 mm", "Lug Width": "16.00 mm", "W/R": "100.00 m", "Nickname": "Trophy", "Color": "Black", "Indexes": "Stick / Dot", "Hands": "Stick"}, "image_url": "https://cdn.watchbase.com/watch/lg/breitling/galactic/a7133053-bf62-235x-b1.jpg"}, {"slug": "a7133053-bf62-777p-a14ba-1", "url": "/breitling/galactic/a7133053-bf62-777p-a14ba-1", "collection": "Galactic watches1255", "title": "Breitling - A7133053/BF62/777P/A14BA.1 Galactic 32 Sleek Edition Stainless Steel / Diamond / Trophy Black / Croco", "specs": {"Brand": "Breitling", "Family": "Galactic", "Reference": "A7133053/BF62/777P/A14BA.1", "Name": "Galactic 32 Sleek Edition Stainless Steel / Diamond / Trophy Black / Croco", "Movement": "Breitling caliber Caliber B71 Hours, Minutes, Seconds | Date | Chronometer", "Produced": "2017", "Limited": "No", "Material": "Stainless Steel", "Glass": "Sapphire", "Back": "Closed", "Shape": "Round", "Diameter": "32.00 mm", "Height": "10.95 mm", "Lug Width": "16.00 mm", "W/R": "100.00 m", "Nickname": "Trophy", "Color": "Black", "Indexes": "Stick / Dot", "Hands": "Stick"}, "image_url": "https://cdn.watchbase.com/watch/lg/breitling/galactic/a7133053-bf62-777p-ba.jpg"}, {"slug": "a7133053-bf62-164s-a14s-1", "url": "/breitling/galactic/a7133053-bf62-164s-a14s-1", "collection": "Galactic watches1255", "title": "Breitling - A7133053/BF62/164S/A14S.1 Galactic 32 Sleek Edition Stainless Steel / Diamond / Trophy Black / Rubber", "specs": {"Brand": "Breitling", "Family": "Galactic", "Reference": "A7133053/BF62/164S/A14S.1", "Name": "Galactic 32 Sleek Edition Stainless Steel / Diamond / Trophy Black / Rubber", "Movement": "Breitling caliber Caliber B71 Hours, Minutes, Seconds | Date | Chronometer", "Produced": "2017", "Limited": "No", "Material": "Stainless Steel", "Glass": "Sapphire", "Back": "Closed", "Shape": "Round", "Diameter": "32.00 mm", "Height": "10.95 mm", "Lug Width": "16.00 mm", "W/R": "100.00 m", "Nickname": "Trophy", "Color": "Black", "Indexes": "Stick / Dot", "Hands": "Stick"}, "image_url": "https://cdn.watchbase.com/watch/lg/breitling/galactic/a7133053-bf62-164s-79.jpg"}, {"slug": "a7133053-c966-209x-a14ba-1", "url": "/breitling/galactic/a7133053-c966-209x-a14ba-1", "collection": "Galactic watches1255", "title": "Breitling - A7133053/C966/209X/A14BA.1 Galactic 32 Sleek Edition Stainless Steel / Diamond / Horizon Blue Diamond / Sahara", "specs": {"Brand": "Breitling", "Family": "Galactic", "Reference": "A7133053/C966/209X/A14BA.1", "Name": "Galactic 32 Sleek Edition Stainless Steel / Diamond / Horizon Blue Diamond / Sahara", "Movement": "Breitling caliber Caliber B71 Hours, Minutes, Seconds | Date | Chronometer", "Produced": "2017", "Limited": "No", "Material": "Stainless Steel", "Glass": "Sapphire", "Back": "Closed", "Shape": "Round", "Diameter": "32.00 mm", "Height": "10.95 mm", "Lug Width": "16.00 mm", "W/R": "100.00 m", "Nickname": "Horizon", "Color": "Blue", "Indexes": "Gem-Set Indexes", "Hands": "Stick"}, "image_url": "https://cdn.watchbase.com/watch/lg/breitling/galactic/a7133053-c966-209x-d6.jpg"}, {"slug": "a7133053-c966-778p-a14ba-1", "url": "/breitling/galactic/a7133053-c966-778p-a14ba-1", "collection": "Galactic watches1255", "title": "Breitling - A7133053/C966/778P/A14BA.1 Galactic 32 Sleek Edition Stainless Steel / Diamond / Horizon Blue Diamond / Croco", "specs": {"Brand": "Breitling", "Family": "Galactic", "Reference": "A7133053/C966/778P/A14BA.1", "Name": "Galactic 32 Sleek Edition Stainless Steel / Diamond / Horizon Blue Diamond / Croco", "Movement": "Breitling caliber Caliber B71 Hours, Minutes, Seconds | Date | Chronometer", "Produced": "2017", "Limited": "No", "Material": "Stainless Steel", "Glass": "Sapphire", "Back": "Closed", "Shape": "Round", "Diameter": "32.00 mm", "Height": "10.95 mm", "Lug Width": "16.00 mm", "W/R": "100.00 m", "Nickname": "Horizon", "Color": "Blue", "Indexes": "Gem-Set Indexes", "Hands": "Stick"}, "image_url": "https://cdn.watchbase.com/watch/lg/breitling/galactic/a7133053-c966-778p-1e.jpg"}, {"slug": "a7133053-c966-164s-a14s-1", "url": "/breitling/galactic/a7133053-c966-164s-a14s-1", "collection": "Galactic watches1255", "title": "Breitling - A7133053/C966/164S/A14S.1 Galactic 32 Sleek Edition Stainless Steel / Diamond / Horizon Blue Diamond / Rubber", "specs": {"Brand": "Breitling", "Family": "Galactic", "Reference": "A7133053/C966/164S/A14S.1", "Name": "Galactic 32 Sleek Edition Stainless Steel / Diamond / Horizon Blue Diamond / Rubber", "Movement": "Breitling caliber Caliber B71 Hours, Minutes, Seconds | Date | Chronometer", "Produced": "2017", "Limited": "No", "Material": "Stainless Steel", "Glass": "Sapphire", "Back": "Closed", "Shape": "Round", "Diameter": "32.00 mm", "Height": "10.95 mm", "Lug Width": "16.00 mm", "W/R": "100.00 m", "Nickname": "Horizon", "Color": "Blue", "Indexes": "Gem-Set Indexes", "Hands": "Stick"}, "image_url": "https://cdn.watchbase.com/watch/lg/breitling/galactic/a7133053-c966-164s-db.jpg"}, {"slug": "a7133053-a801-406x-a14ba-1", "url": "/breitling/galactic/a7133053-a801-406x-a14ba-1", "collection": "Galactic watches1255", "title": "Breitling - A7133053/A801/406X/A14BA.1 Galactic 32 Sleek Edition Stainless Steel / Diamond / Pearl Diamond / Calf", "specs": {"Brand": "Breitling", "Family": "Galactic", "Reference": "A7133053/A801/406X/A14BA.1", "Name": "Galactic 32 Sleek Edition Stainless Steel / Diamond / Pearl Diamond / Calf", "Movement": "Breitling caliber Caliber B71 Hours, Minutes, Seconds | Date | Chronometer", "Produced": "2017", "Limited": "No", "Material": "Mother of Pearl", "Glass": "Sapphire", "Back": "Closed", "Shape": "Round", "Diameter": "32.00 mm", "Height": "10.95 mm", "Lug Width": "16.00 mm", "W/R": "100.00 m", "Color": "White", "Indexes": "Gem-Set Indexes", "Hands": "Stick"}, "image_url": "https://cdn.watchbase.com/watch/lg/breitling/galactic/a7133053-a801-406x-77.jpg"}, {"slug": "a7133053-a801-209x-a14ba-1", "url": "/breitling/galactic/a7133053-a801-209x-a14ba-1", "collection": "Galactic watches1255", "title": "Breitling - A7133053/A801/209X/A14BA.1 Galactic 32 Sleek Edition Stainless Steel / Diamond / Pearl Diamond / Sahara", "specs": {"Brand": "Breitling", "Family": "Galactic", "Reference": "A7133053/A801/209X/A14BA.1", "Name": "Galactic 32 Sleek Edition Stainless Steel / Diamond / Pearl Diamond / Sahara", "Movement": "Breitling caliber Caliber B71 Hours, Minutes, Seconds | Date | Chronometer", "Produced": "2017", "Limited": "No", "Material": "Mother of Pearl", "Glass": "Sapphire", "Back": "Closed", "Shape": "Round", "Diameter": "32.00 mm", "Height": "10.95 mm", "Lug Width": "16.00 mm", "W/R": "100.00 m", "Color": "White", "Indexes": "Gem-Set Indexes", "Hands": "Stick"}, "image_url": "https://cdn.watchbase.com/watch/lg/breitling/galactic/a7133053-a801-209x-a0.jpg"}, {"slug": "a7133053-a801-777p-a14ba-1", "url": "/breitling/galactic/a7133053-a801-777p-a14ba-1", "collection": "Galactic watches1255", "title": "Breitling - A7133053/A801/777P/A14BA.1 Galactic 32 Sleek Edition Stainless Steel / Diamond / Pearl Diamond / Croco", "specs": {"Brand": "Breitling", "Family": "Galactic", "Reference": "A7133053/A801/777P/A14BA.1", "Name": "Galactic 32 Sleek Edition Stainless Steel / Diamond / Pearl Diamond / Croco", "Movement": "Breitling caliber Caliber B71 Hours, Minutes, Seconds | Date | Chronometer", "Produced": "2017", "Limited": "No", "Material": "Mother of Pearl", "Glass": "Sapphire", "Back": "Closed", "Shape": "Round", "Diameter": "32.00 mm", "Height": "10.95 mm", "Lug Width": "16.00 mm", "W/R": "100.00 m", "Color": "White", "Indexes": "Gem-Set Indexes", "Hands": "Stick"}, "image_url": "https://cdn.watchbase.com/watch/lg/breitling/galactic/a7133053-a801-777p-6b.jpg"}, {"slug": "a7133053-a801-164s-a14s-1", "url": "/breitling/galactic/a7133053-a801-164s-a14s-1", "collection": "Galactic watches1255", "title": "Breitling - A7133053/A801/164S/A14S.1 Galactic 32 Sleek Edition Stainless Steel / Diamond / Pearl Diamond / Rubber", "specs": {"Brand": "Breitling", "Family": "Galactic", "Reference": "A7133053/A801/164S/A14S.1", "Name": "Galactic 32 Sleek Edition Stainless Steel / Diamond / Pearl Diamond / Rubber", "Movement": "Breitling caliber Caliber B71 Hours, Minutes, Seconds | Date | Chronometer", "Produced": "2017", "Limited": "No", "Material": "Mother of Pearl", "Glass": "Sapphire", "Back": "Closed", "Shape": "Round", "Diameter": "32.00 mm", "Height": "10.95 mm", "Lug Width": "16.00 mm", "W/R": "100.00 m", "Color": "White", "Indexes": "Gem-Set Indexes", "Hands": "Stick"}, "image_url": "https://cdn.watchbase.com/watch/lg/breitling/galactic/a7133053-a801-164s-b6.jpg"}, {"slug": "a7133053-bf63-408x-a14ba-1", "url": "/breitling/galactic/a7133053-bf63-408x-a14ba-1", "collection": "Galactic watches1255", "title": "Breitling - A7133053/BF63/408X/A14BA.1 Galactic 32 Sleek Edition Stainless Steel / Diamond / Trophy Black Diamond / Calf", "specs": {"Brand": "Breitling", "Family": "Galactic", "Reference": "A7133053/BF63/408X/A14BA.1", "Name": "Galactic 32 Sleek Edition Stainless Steel / Diamond / Trophy Black Diamond / Calf", "Movement": "Breitling caliber Caliber B71 Hours, Minutes, Seconds | Date | Chronometer", "Produced": "2017", "Limited": "No", "Material": "Stainless Steel", "Glass": "Sapphire", "Back": "Closed", "Shape": "Round", "Diameter": "32.00 mm", "Height": "10.95 mm", "Lug Width": "16.00 mm", "W/R": "100.00 m", "Nickname": "Trophy", "Color": "Black", "Indexes": "Gem-Set Indexes", "Hands": "Stick"}, "image_url": "https://cdn.watchbase.com/watch/lg/breitling/galactic/a7133053-bf63-408x-a6.jpg"}, {"slug": "a7133053-bf63-235x-a14ba-1", "url": "/breitling/galactic/a7133053-bf63-235x-a14ba-1", "collection": "Galactic watches1255", "title": "Breitling - A7133053/BF63/235X/A14BA.1 Galactic 32 Sleek Edition Stainless Steel / Diamond / Trophy Black Diamond / Sahara", "specs": {"Brand": "Breitling", "Family": "Galactic", "Reference": "A7133053/BF63/235X/A14BA.1", "Name": "Galactic 32 Sleek Edition Stainless Steel / Diamond / Trophy Black Diamond / Sahara", "Movement": "Breitling caliber Caliber B71 Hours, Minutes, Seconds | Date | Chronometer", "Produced": "2017", "Limited": "No", "Material": "Stainless Steel", "Glass": "Sapphire", "Back": "Closed", "Shape": "Round", "Diameter": "32.00 mm", "Height": "10.95 mm", "Lug Width": "16.00 mm", "W/R": "100.00 m", "Nickname": "Trophy", "Color": "Black", "Indexes": "Gem-Set Indexes", "Hands": "Stick"}, "image_url": "https://cdn.watchbase.com/watch/lg/breitling/galactic/a7133053-bf63-235x-be.jpg"}, {"slug": "a7133053-bf63-778p-a14ba-1", "url": "/breitling/galactic/a7133053-bf63-778p-a14ba-1", "collection": "Galactic watches1255", "title": "Breitling - A7133053/BF63/778P/A14BA.1 Galactic 32 Sleek Edition Stainless Steel / Diamond / Trophy Black Diamond / Croco", "specs": {"Brand": "Breitling", "Family": "Galactic", "Reference": "A7133053/BF63/778P/A14BA.1", "Name": "Galactic 32 Sleek Edition Stainless Steel / Diamond / Trophy Black Diamond / Croco", "Movement": "Breitling caliber Caliber B71 Hours, Minutes, Seconds | Date | Chronometer", "Produced": "2017", "Limited": "No", "Material": "Stainless Steel", "Glass": "Sapphire", "Back": "Closed", "Shape": "Round", "Diameter": "32.00 mm", "Height": "10.95 mm", "Lug Width": "16.00 mm", "W/R": "100.00 m", "Nickname": "Trophy", "Color": "Black", "Indexes": "Gem-Set Indexes", "Hands": "Stick"}, "image_url": "https://cdn.watchbase.com/watch/lg/breitling/galactic/a7133053-bf63-778p-46.jpg"}, {"slug": "c7133012-a803-792c", "url": "/breitling/galactic/c7133012-a803-792c", "collection": "Galactic watches1255", "title": "Breitling - C7133012/A803/792C Galactic 32 Sleek Edition Stainless Steel / Rose Gold / Pearl Diamond / Bracelet", "specs": {"Brand": "Breitling", "Family": "Galactic", "Reference": "C7133012/A803/792C", "Name": "Galactic 32 Sleek Edition Stainless Steel / Rose Gold / Pearl Diamond / Bracelet", "Movement": "Breitling caliber Caliber B71 Hours, Minutes, Seconds | Date | Chronometer", "Produced": "2017", "Limited": "No", "Materials": "Rose Gold, Stainless Steel", "Glass": "Sapphire", "Back": "Closed", "Shape": "Round", "Diameter": "32.00 mm", "Height": "10.95 mm", "Lug Width": "16.00 mm", "W/R": "100.00 m", "Color": "White", "Material": "Mother of Pearl", "Indexes": "Gem-Set Indexes", "Hands": "Stick"}, "image_url": "https://cdn.watchbase.com/watch/lg/breitling/galactic/c7133012-a803-792c-7f.jpg"}, {"slug": "c7133053-c952-792c", "url": "/breitling/galactic/c7133053-c952-792c", "collection": "Galactic watches1255", "title": "Breitling - C7133053/C952/792C Galactic 32 Sleek Edition Stainless Steel / Rose Gold / Diamond / Horizon Blue / Bracelet", "specs": {"Brand": "Breitling", "Family": "Galactic", "Reference": "C7133053/C952/792C", "Name": "Galactic 32 Sleek Edition Stainless Steel / Rose Gold / Diamond / Horizon Blue / Bracelet", "Movement": "Breitling caliber Caliber B71 Hours, Minutes, Seconds | Date | Chronometer", "Produced": "2017", "Limited": "No", "Materials": "Rose Gold, Stainless Steel", "Bezel": "Gem-Set", "Glass": "Sapphire", "Back": "Closed", "Shape": "Round", "Diameter": "32.00 mm", "Height": "10.95 mm", "Lug Width": "16.00 mm", "W/R": "100.00 m", "Nickname": "Horizon", "Color": "Blue", "Indexes": "Stick / Dot", "Hands": "Stick"}, "image_url": "https://cdn.watchbase.com/watch/lg/breitling/galactic/c7133053-c952-792c-7d.jpg"}, {"slug": "c7133053-h550-792c-a14ba-1", "url": "/breitling/galactic/c7133053-h550-792c-a14ba-1", "collection": "Galactic watches1255", "title": "Breitling - C7133053/H550/792C/A14BA.1 Galactic 32 Sleek Edition Stainless Steel / Rose Gold / Diamond / Golden Sun Diamond / Bracelet", "specs": {"Brand": "Breitling", "Family": "Galactic", "Reference": "C7133053/H550/792C/A14BA.1", "Name": "Galactic 32 Sleek Edition Stainless Steel / Rose Gold / Diamond / Golden Sun Diamond / Bracelet", "Movement": "Breitling caliber Caliber B71 Hours, Minutes, Seconds | Date | Chronometer", "Produced": "2017", "Limited": "No", "Materials": "Rose Gold, Stainless Steel", "Bezel": "Gem-Set", "Glass": "Sapphire", "Back": "Closed", "Shape": "Round", "Diameter": "32.00 mm", "Height": "10.95 mm", "Lug Width": "16.00 mm", "W/R": "100.00 m", "Nickname": "Golden Sun", "Color": "Champagne", "Indexes": "Gem-Set Indexes", "Hands": "Stick"}, "image_url": "https://cdn.watchbase.com/watch/lg/breitling/galactic/c7133053-h550-792c-f4.jpg"}, {"slug": "c7133012-a802-211x-a14ba-1", "url": "/breitling/galactic/c7133012-a802-211x-a14ba-1", "collection": "Galactic watches1255", "title": "Breitling - C7133012/A802/211X/A14BA.1 Galactic 32 Sleek Edition Stainless Steel / Rose Gold / Pearl / Sahara", "specs": {"Brand": "Breitling", "Family": "Galactic", "Reference": "C7133012/A802/211X/A14BA.1", "Name": "Galactic 32 Sleek Edition Stainless Steel / Rose Gold / Pearl / Sahara", "Movement": "Breitling caliber Caliber B71 Hours, Minutes, Seconds | Date | Chronometer", "Produced": "2017", "Limited": "No", "Materials": "Rose Gold, Stainless Steel", "Glass": "Sapphire", "Back": "Closed", "Shape": "Round", "Diameter": "32.00 mm", "Height": "10.95 mm", "Lug Width": "16.00 mm", "W/R": "100.00 m", "Color": "White", "Material": "Mother of Pearl", "Indexes": "Stick / Dot", "Hands": "Stick"}, "image_url": "https://cdn.watchbase.com/watch/lg/breitling/galactic/c7133012-a802-211x-b8.jpg"}, {"slug": "c7133012-a802-235x-a14ba-1", "url": "/breitling/galactic/c7133012-a802-235x-a14ba-1", "collection": "Galactic watches1255", "title": "Breitling - C7133012/A802/235X/A14BA.1 Galactic 32 Sleek Edition Stainless Steel / Rose Gold / Pearl / Sahara", "specs": {"Brand": "Breitling", "Family": "Galactic", "Reference": "C7133012/A802/235X/A14BA.1", "Name": "Galactic 32 Sleek Edition Stainless Steel / Rose Gold / Pearl / Sahara", "Movement": "Breitling caliber Caliber B71 Hours, Minutes, Seconds | Date | Chronometer", "Produced": "2017", "Limited": "No", "Materials": "Rose Gold, Stainless Steel", "Glass": "Sapphire", "Back": "Closed", "Shape": "Round", "Diameter": "32.00 mm", "Height": "10.95 mm", "Lug Width": "16.00 mm", "W/R": "100.00 m", "Color": "White", "Material": "Mother of Pearl", "Indexes": "Stick / Dot", "Hands": "Stick"}, "image_url": "https://cdn.watchbase.com/watch/lg/breitling/galactic/c7133012-a802-235x-63.jpg"}, {"slug": "c7133012-bf65-408x-a14ba-1", "url": "/breitling/galactic/c7133012-bf65-408x-a14ba-1", "collection": "Galactic watches1255", "title": "Breitling - C7133012/BF65/408X/A14BA.1 Galactic 32 Sleek Edition Stainless Steel / Rose Gold / Trophy Black / Calf", "specs": {"Brand": "Breitling", "Family": "Galactic", "Reference": "C7133012/BF65/408X/A14BA.1", "Name": "Galactic 32 Sleek Edition Stainless Steel / Rose Gold / Trophy Black / Calf", "Movement": "Breitling caliber Caliber B71 Hours, Minutes, Seconds | Date | Chronometer", "Produced": "2017", "Limited": "No", "Materials": "Rose Gold, Stainless Steel", "Glass": "Sapphire", "Back": "Closed", "Shape": "Round", "Diameter": "32.00 mm", "Height": "10.95 mm", "Lug Width": "16.00 mm", "W/R": "100.00 m", "Nickname": "Trophy", "Color": "Black", "Indexes": "Stick / Dot", "Hands": "Stick"}, "image_url": "https://cdn.watchbase.com/watch/lg/breitling/galactic/c7133012-bf65-408x-f7.jpg"}, {"slug": "c7133012-bf65-778p-a14ba-1", "url": "/breitling/galactic/c7133012-bf65-778p-a14ba-1", "collection": "Galactic watches1255", "title": "Breitling - C7133012/BF65/778P/A14BA.1 Galactic 32 Sleek Edition Stainless Steel / Rose Gold / Trophy Black / Croco", "specs": {"Brand": "Breitling", "Family": "Galactic", "Reference": "C7133012/BF65/778P/A14BA.1", "Name": "Galactic 32 Sleek Edition Stainless Steel / Rose Gold / Trophy Black / Croco", "Movement": "Breitling caliber Caliber B71 Hours, Minutes, Seconds | Date | Chronometer", "Produced": "2017", "Limited": "No", "Materials": "Rose Gold, Stainless Steel", "Glass": "Sapphire", "Back": "Closed", "Shape": "Round", "Diameter": "32.00 mm", "Height": "10.95 mm", "Lug Width": "16.00 mm", "W/R": "100.00 m", "Nickname": "Trophy", "Color": "Black", "Indexes": "Stick / Dot", "Hands": "Stick"}, "image_url": "https://cdn.watchbase.com/watch/lg/breitling/galactic/c7133012-bf65-778p-b4.jpg"}, {"slug": "c7133012-bf65-164s-a14s-1", "url": "/breitling/galactic/c7133012-bf65-164s-a14s-1", "collection": "Galactic watches1255", "title": "Breitling - C7133012/BF65/164S/A14S.1 Galactic 32 Sleek Edition Stainless Steel / Rose Gold / Trophy Black / Rubber", "specs": {"Brand": "Breitling", "Family": "Galactic", "Reference": "C7133012/BF65/164S/A14S.1", "Name": "Galactic 32 Sleek Edition Stainless Steel / Rose Gold / Trophy Black / Rubber", "Movement": "Breitling caliber Caliber B71 Hours, Minutes, Seconds | Date | Chronometer", "Produced": "2017", "Limited": "No", "Materials": "Rose Gold, Stainless Steel", "Glass": "Sapphire", "Back": "Closed", "Shape": "Round", "Diameter": "32.00 mm", "Height": "10.95 mm", "Lug Width": "16.00 mm", "W/R": "100.00 m", "Nickname": "Trophy", "Color": "Black", "Indexes": "Stick / Dot", "Hands": "Stick"}, "image_url": "https://cdn.watchbase.com/watch/lg/breitling/galactic/c7133012-bf65-164s-ee.jpg"}, {"slug": "c7133012-bf65-116x-a14ba-1", "url": "/breitling/galactic/c7133012-bf65-116x-a14ba-1", "collection": "Galactic watches1255", "title": "Breitling - C7133012/BF65/116X/A14BA.1 Galactic 32 Sleek Edition Stainless Steel / Rose Gold / Horizon Blue / Calf", "specs": {"Brand": "Breitling", "Family": "Galactic", "Reference": "C7133012/BF65/116X/A14BA.1", "Name": "Galactic 32 Sleek Edition Stainless Steel / Rose Gold / Horizon Blue / Calf", "Movement": "Breitling caliber Caliber B71 Hours, Minutes, Seconds | Date | Chronometer", "Produced": "2017", "Limited": "No", "Materials": "Rose Gold, Stainless Steel", "Glass": "Sapphire", "Back": "Closed", "Shape": "Round", "Diameter": "32.00 mm", "Height": "10.95 mm", "Lug Width": "16.00 mm", "W/R": "100.00 m", "Nickname": "Horizon", "Color": "Blue", "Indexes": "Stick / Dot", "Hands": "Stick"}, "image_url": "https://cdn.watchbase.com/watch/lg/breitling/galactic/c7133012-c952-116x-9e.jpg"}, {"slug": "c7133012-c952-212x-a14ba-1", "url": "/breitling/galactic/c7133012-c952-212x-a14ba-1", "collection": "Galactic watches1255", "title": "Breitling - C7133012/C952/212X/A14BA.1 Galactic 32 Sleek Edition Stainless Steel / Rose Gold / Horizon Blue / Sahara", "specs": {"Brand": "Breitling", "Family": "Galactic", "Reference": "C7133012/C952/212X/A14BA.1", "Name": "Galactic 32 Sleek Edition Stainless Steel / Rose Gold / Horizon Blue / Sahara", "Movement": "Breitling caliber Caliber B71 Hours, Minutes, Seconds | Date | Chronometer", "Produced": "2017", "Limited": "No", "Materials": "Rose Gold, Stainless Steel", "Glass": "Sapphire", "Back": "Closed", "Shape": "Round", "Diameter": "32.00 mm", "Height": "10.95 mm", "Lug Width": "16.00 mm", "W/R": "100.00 m", "Nickname": "Horizon", "Color": "Blue", "Indexes": "Stick / Dot", "Hands": "Stick"}, "image_url": "https://cdn.watchbase.com/watch/lg/breitling/galactic/c7133012-c952-212x-9.jpg"}, {"slug": "c7133012-c952-778p-a14ba-1", "url": "/breitling/galactic/c7133012-c952-778p-a14ba-1", "collection": "Galactic watches1255", "title": "Breitling - C7133012/C952/778P/A14BA.1 Galactic 32 Sleek Edition Stainless Steel / Rose Gold / Horizon Blue / Croco", "specs": {"Brand": "Breitling", "Family": "Galactic", "Reference": "C7133012/C952/778P/A14BA.1", "Name": "Galactic 32 Sleek Edition Stainless Steel / Rose Gold / Horizon Blue / Croco", "Movement": "Breitling caliber Caliber B71 Hours, Minutes, Seconds | Date | Chronometer", "Produced": "2017", "Limited": "No", "Materials": "Rose Gold, Stainless Steel", "Glass": "Sapphire", "Back": "Closed", "Shape": "Round", "Diameter": "32.00 mm", "Height": "10.95 mm", "Lug Width": "16.00 mm", "W/R": "100.00 m", "Nickname": "Horizon", "Color": "Blue", "Indexes": "Stick / Dot", "Hands": "Stick"}, "image_url": "https://cdn.watchbase.com/watch/lg/breitling/galactic/c7133012-c952-778p-92.jpg"}, {"slug": "c7133012-c952-777p-a14ba-1", "url": "/breitling/galactic/c7133012-c952-777p-a14ba-1", "collection": "Galactic watches1255", "title": "Breitling - C7133012/C952/777P/A14BA.1 Galactic 32 Sleek Edition Stainless Steel / Rose Gold / Horizon Blue / Croco", "specs": {"Brand": "Breitling", "Family": "Galactic", "Reference": "C7133012/C952/777P/A14BA.1", "Name": "Galactic 32 Sleek Edition Stainless Steel / Rose Gold / Horizon Blue / Croco", "Movement": "Breitling caliber Caliber B71 Hours, Minutes, Seconds | Date | Chronometer", "Produced": "2017", "Limited": "No", "Materials": "Rose Gold, Stainless Steel", "Glass": "Sapphire", "Back": "Closed", "Shape": "Round", "Diameter": "32.00 mm", "Height": "10.95 mm", "Lug Width": "16.00 mm", "W/R": "100.00 m", "Nickname": "Horizon", "Color": "Blue", "Indexes": "Stick / Dot", "Hands": "Stick"}, "image_url": "https://cdn.watchbase.com/watch/lg/breitling/galactic/c7133012-c952-777p-d6.jpg"}, {"slug": "c7133012-h549-406x-a14ba-1", "url": "/breitling/galactic/c7133012-h549-406x-a14ba-1", "collection": "Galactic watches1255", "title": "Breitling - C7133012/H549/406X/A14BA.1 Galactic 32 Sleek Edition Stainless Steel / Rose Gold / Golden Sun / Calf", "specs": {"Brand": "Breitling", "Family": "Galactic", "Reference": "C7133012/H549/406X/A14BA.1", "Name": "Galactic 32 Sleek Edition Stainless Steel / Rose Gold / Golden Sun / Calf", "Movement": "Breitling caliber Caliber B71 Hours, Minutes, Seconds | Date | Chronometer", "Produced": "2017", "Limited": "No", "Materials": "Rose Gold, Stainless Steel", "Glass": "Sapphire", "Back": "Closed", "Shape": "Round", "Diameter": "32.00 mm", "Height": "10.95 mm", "Lug Width": "16.00 mm", "W/R": "100.00 m", "Nickname": "Golden Sun", "Color": "Champagne", "Indexes": "Stick / Dot", "Hands": "Stick"}, "image_url": "https://cdn.watchbase.com/watch/lg/breitling/galactic/c7133012-h549-406x-9d.jpg"}, {"slug": "c7133012-h549-410x-a14ba-1", "url": "/breitling/galactic/c7133012-h549-410x-a14ba-1", "collection": "Galactic watches1255", "title": "Breitling - C7133012/H549/410X/A14BA.1 Galactic 32 Sleek Edition Stainless Steel / Rose Gold / Golden Sun / Calf", "specs": {"Brand": "Breitling", "Family": "Galactic", "Reference": "C7133012/H549/410X/A14BA.1", "Name": "Galactic 32 Sleek Edition Stainless Steel / Rose Gold / Golden Sun / Calf", "Movement": "Breitling caliber Caliber B71 Hours, Minutes, Seconds | Date | Chronometer", "Produced": "2017", "Limited": "No", "Materials": "Rose Gold, Stainless Steel", "Glass": "Sapphire", "Back": "Closed", "Shape": "Round", "Diameter": "32.00 mm", "Height": "10.95 mm", "Lug Width": "16.00 mm", "W/R": "100.00 m", "Nickname": "Golden Sun", "Color": "Champagne", "Indexes": "Stick / Dot", "Hands": "Stick"}, "image_url": "https://cdn.watchbase.com/watch/lg/breitling/galactic/c7133012-h549-410x-f2.jpg"}, {"slug": "c7133012-bf64-408x-a14ba-1", "url": "/breitling/galactic/c7133012-bf64-408x-a14ba-1", "collection": "Galactic watches1255", "title": "Breitling - C7133012/BF64/408X/A14BA.1 Galactic 32 Sleek Edition Stainless Steel / Rose Gold / Trophy Black Diamond / Calf", "specs": {"Brand": "Breitling", "Family": "Galactic", "Reference": "C7133012/BF64/408X/A14BA.1", "Name": "Galactic 32 Sleek Edition Stainless Steel / Rose Gold / Trophy Black Diamond / Calf", "Movement": "Breitling caliber Caliber B71 Hours, Minutes, Seconds | Date | Chronometer", "Produced": "2017", "Limited": "No", "Materials": "Rose Gold, Stainless Steel", "Glass": "Sapphire", "Back": "Closed", "Shape": "Round", "Diameter": "32.00 mm", "Height": "10.95 mm", "Lug Width": "16.00 mm", "W/R": "100.00 m", "Nickname": "Trophy", "Color": "Black", "Indexes": "Gem-Set Indexes", "Hands": "Stick"}, "image_url": "https://cdn.watchbase.com/watch/lg/breitling/galactic/c7133012-bf64-408x-75.jpg"}, {"slug": "c7133012-bf64-208x-a14ba-1", "url": "/breitling/galactic/c7133012-bf64-208x-a14ba-1", "collection": "Galactic watches1255", "title": "Breitling - C7133012/BF64/208X/A14BA.1 Galactic 32 Sleek Edition Stainless Steel / Rose Gold / Trophy Black Diamond / Sahara", "specs": {"Brand": "Breitling", "Family": "Galactic", "Reference": "C7133012/BF64/208X/A14BA.1", "Name": "Galactic 32 Sleek Edition Stainless Steel / Rose Gold / Trophy Black Diamond / Sahara", "Movement": "Breitling caliber Caliber B71 Hours, Minutes, Seconds | Date | Chronometer", "Produced": "2017", "Limited": "No", "Materials": "Rose Gold, Stainless Steel", "Glass": "Sapphire", "Back": "Closed", "Shape": "Round", "Diameter": "32.00 mm", "Height": "10.95 mm", "Lug Width": "16.00 mm", "W/R": "100.00 m", "Nickname": "Trophy", "Color": "Black", "Indexes": "Gem-Set Indexes", "Hands": "Stick"}, "image_url": "https://cdn.watchbase.com/watch/lg/breitling/galactic/c7133012-bf64-208x-34.jpg"}]}