{"name": "Prospex Divers watches62", "slug": "prospex-divers", "references": [{"slug": "srp789", "url": "/seiko/prospex-divers/srp789", "collection": "Prospex Divers watches62", "title": "Seiko - SRP789 Prospex Diver Turtle Stainless Steel / Black / Bracelet / Coke", "specs": {"Brand": "Seiko", "Family": "Prospex Divers", "Reference": "SRP789 (aka: SRP789K1)", "Name": "Prospex Diver Turtle Stainless Steel / Black / Bracelet / Coke", "Movement": "Seiko caliber 4R36 Hours, Minutes, Seconds | Date, Day", "Produced": "2016", "Limited": "No", "Material": "Stainless Steel", "Bezel": "Rotating, 0-60 (Dive)", "Glass": "Hardlex", "Back": "Closed", "Shape": "Cushion", "Diameter": "45.00 mm", "Height": "13.50 mm", "Lug Width": "22.00 mm", "W/R": "200.00 m", "Color": "Blue", "Finish": "Matte", "Indexes": "Stick / Dot", "Hands": "Arrow"}, "image_url": "/watches/seiko/prospex-divers/srp789.jpg", "image_url_source": "https://cdn.watchbase.com/watch/lg/seiko/prospex-divers/srp789-3b.jpg"}, {"slug": "srpb49", "url": "/seiko/prospex-divers/srpb49", "collection": "Prospex Divers watches62", "title": "Seiko - SRPB49 Prospex Diver Samurai Stainless Steel / Blue / Bracelet", "specs": {"Brand": "Seiko", "Family": "Prospex Divers", "Reference": "SRPB49 (aka: SRPB49K1)", "Name": "Prospex Diver Samurai Stainless Steel / Blue / Bracelet", "Movement": "Seiko caliber 4R35 Hours, Minutes, Seconds | Date", "Produced": "2017", "Limited": "No", "Material": "Stainless Steel", "Bezel": "Rotating, 0-60 (Dive)", "Glass": "Hardlex", "Back": "Closed", "Shape": "Round", "Diameter": "43.80 mm", "Lug Width": "22.00 mm", "W/R": "200.00 m", "Color": "Blue", "Finish": "Matte", "Indexes": "Stick / Dot", "Hands": "Arrow"}, "image_url": "/watches/seiko/prospex-divers/srpb49.jpg", "image_url_source": "https://cdn.watchbase.com/watch/lg/seiko/prospex-divers/srpb49k1-10.jpg"}, {"slug": "srpa19", "url": "/seiko/prospex-divers/srpa19", "collection": "Prospex Divers watches62", "title": "Seiko - SRPA19 Prospex Diver Turtle Stainless Steel / Grey / Bracelet / Zimbe", "specs": {"Brand": "Seiko", "Family": "Prospex Divers", "Reference": "SRPA19 (aka: SRPA19K1)", "Name": "Prospex Diver Turtle Stainless Steel / Grey / Bracelet / Zimbe", "Movement": "Seiko caliber 4R36 Hours, Minutes, Seconds | Date, Day", "Produced": "2017", "Limited": "Yes, 1299 units", "Material": "Stainless Steel", "Bezel": "Rotating, 0-60 (Dive)", "Glass": "Sapphire", "Back": "Closed", "Shape": "Cushion", "Diameter": "45.00 mm", "Height": "13.50 mm", "Lug Width": "22.00 mm", "W/R": "200.00 m", "Color": "Grey", "Finish": "Matte", "Indexes": "Stick / Dot", "Hands": "Arrow"}, "image_url": "/watches/seiko/prospex-divers/srpa19.jpg", "image_url_source": "https://cdn.watchbase.com/watch/lg/seiko/prospex-divers/srpa19-a9.png"}, {"slug": "srpb97", "url": "/seiko/prospex-divers/srpb97", "collection": "Prospex Divers watches62", "title": "Seiko - SRPB97 Prospex Diver Samurai Stainless Steel / Orange / Bracelet", "specs": {"Brand": "Seiko", "Family": "Prospex Divers", "Reference": "SRPB97", "Name": "Prospex Diver Samurai Stainless Steel / Orange / Bracelet", "Movement": "Seiko caliber 4R35 Hours, Minutes, Seconds | Date", "Produced": "2017", "Limited": "No", "Material": "Stainless Steel", "Bezel": "Rotating, 0-60 (Dive)", "Glass": "Hardlex", "Back": "Closed", "Shape": "Round", "Diameter": "43.80 mm", "Lug Width": "22.00 mm", "W/R": "200.00 m", "Color": "Black", "Finish": "Matte", "Indexes": "Stick / Dot", "Hands": "Arrow"}, "image_url": "/watches/seiko/prospex-divers/srpb97.jpg", "image_url_source": "https://cdn.watchbase.com/watch/lg/seiko/prospex-divers/srpb97-aa.jpg"}, {"slug": "srpb01", "url": "/seiko/prospex-divers/srpb01", "collection": "Prospex Divers watches62", "title": "Seiko - SRPB01 Prospex Diver Turtle Stainless Steel / Green / Bracelet", "specs": {"Brand": "Seiko", "Family": "Prospex Divers", "Reference": "SRPB01 (aka: SRPB01K1)", "Name": "Prospex Diver Turtle Stainless Steel / Green / Bracelet", "Movement": "Seiko caliber 4R36 Hours, Minutes, Seconds | Date, Day", "Produced": "2016", "Limited": "Yes, 3500 units", "Material": "Stainless Steel", "Bezel": "Rotating, 0-60 (Dive)", "Glass": "Hardlex", "Back": "Closed", "Shape": "Cushion", "Diameter": "45.00 mm", "Height": "13.50 mm", "Lug Width": "22.00 mm", "W/R": "200.00 m", "Color": "Blue", "Finish": "Matte", "Indexes": "Stick / Dot", "Hands": "Arrow"}, "image_url": "/watches/seiko/prospex-divers/srpb01.jpg", "image_url_source": "https://cdn.watchbase.com/watch/lg/seiko/prospex-divers/srpb01k1-4.jpg"}, {"slug": "srpd21k1", "url": "/seiko/prospex-divers/srpd21k1", "collection": "Prospex Divers watches62", "title": "Seiko - SRPD21K1 Prospex Diver Turtle Stainless Steel / Blue / Bracelet / Save the Ocean", "specs": {"Brand": "Seiko", "Family": "Prospex Divers", "Reference": "SRPD21K1 (aka: SRPD21)", "Name": "Prospex Diver Turtle Stainless Steel / Blue / Bracelet / Save the Ocean", "Movement": "Seiko caliber 4R36 Hours, Minutes, Seconds | Date, Day", "Produced": "2019", "Limited": "No", "Material": "Stainless Steel", "Bezel": "Rotating, 0-60 (Dive)", "Glass": "Hardlex", "Back": "Closed", "Shape": "Cushion", "Diameter": "45.00 mm", "Height": "13.50 mm", "Lug Width": "22.00 mm", "W/R": "200.00 m", "Color": "Blue", "Finish": "Matte", "Indexes": "Stick / Dot", "Hands": "Arrow"}, "image_url": "/watches/seiko/prospex-divers/srpd21k1.jpg", "image_url_source": "https://cdn.watchbase.com/watch/lg/seiko/prospex-divers/srpd21k1-2e.png"}, {"slug": "ssc489p1", "url": "/seiko/prospex-divers/ssc489p1", "collection": "Prospex Divers watches62", "title": "Seiko - SSC489P1 Prospex Diver SSC489P1 Stainless Steel / Blue", "specs": {"Brand": "Seiko", "Family": "Prospex Divers", "Reference": "SSC489P1", "Name": "Prospex Diver SSC489P1 Stainless Steel / Blue", "Movement": "Seiko caliber V195 Hours, Minutes, Seconds, World Time | Solar Charging", "Limited": "No", "Material": "Stainless Steel", "Glass": "Sapphire", "Back": "Closed", "Shape": "Round", "Diameter": "44.60 mm", "Lug Width": "20.00 mm", "W/R": "100.00 m", "Color": "Blue", "Finish": "Sunburst", "Indexes": "Stick / Dot", "Hands": "Stick"}, "image_url": "/watches/seiko/prospex-divers/ssc489p1.jpg", "image_url_source": "https://cdn.watchbase.com/watch/lg/seiko/prospex-divers/ssc489p1-7e.jpg"}, {"slug": "sbdx014g", "url": "/seiko/prospex-divers/sbdx014g", "collection": "Prospex Divers watches62", "title": "Seiko - SBDX014G Prospex Diver SBDX014G Titanium / Black", "specs": {"Brand": "Seiko", "Family": "Prospex Divers", "Reference": "SBDX014G", "Name": "Prospex Diver SBDX014G Titanium / Black", "Movement": "Seiko caliber 8L35 Hours, Minutes, Seconds | Date", "Limited": "No", "Material": "Stainless Steel", "Bezel": "Rotating, 0-60 (Dive)", "Glass": "Sapphire", "Back": "Closed", "Shape": "Cushion", "Diameter": "45.00 mm", "Lug Width": "22.00 mm", "W/R": "1000.00 m", "Color": "Black", "Finish": "Matte", "Indexes": "Stick / Dot", "Hands": "Arrow"}, "image_url": "/watches/seiko/prospex-divers/sbdx014g.jpg", "image_url_source": "https://cdn.watchbase.com/watch/lg/seiko/prospex-divers/sbdx014g-ed.jpg"}, {"slug": "srpc23", "url": "/seiko/prospex-divers/srpc23", "collection": "Prospex Divers watches62", "title": "Seiko - SRPC23 Prospex Diver Turtle Stainless Steel / Grey / Bracelet", "specs": {"Brand": "Seiko", "Family": "Prospex Divers", "Reference": "SRPC23 (aka: SRPC23K1)", "Name": "Prospex Diver Turtle Stainless Steel / Grey / Bracelet", "Movement": "Seiko caliber 4R36 Hours, Minutes, Seconds | Date, Day", "Produced": "2017", "Limited": "No", "Material": "Stainless Steel", "Bezel": "Rotating, 0-60 (Dive)", "Glass": "Hardlex", "Back": "Closed", "Shape": "Cushion", "Diameter": "45.00 mm", "Height": "13.50 mm", "Lug Width": "22.00 mm", "W/R": "200.00 m", "Color": "Grey", "Finish": "Sunburst", "Indexes": "Stick / Dot", "Hands": "Arrow"}, "image_url": "/watches/seiko/prospex-divers/srpc23.jpg", "image_url_source": "https://cdn.watchbase.com/watch/lg/seiko/prospex-divers/srpc23k1-6b.jpg"}, {"slug": "srpc25", "url": "/seiko/prospex-divers/srpc25", "collection": "Prospex Divers watches62", "title": "Seiko - SRPC25 Prospex Diver Turtle Stainless Steel / Blue Gradient / Bracelet", "specs": {"Brand": "Seiko", "Family": "Prospex Divers", "Reference": "SRPC25 (aka: SRPC25K1)", "Name": "Prospex Diver Turtle Stainless Steel / Blue Gradient / Bracelet", "Movement": "Seiko caliber 4R36 Hours, Minutes, Seconds | Date, Day", "Produced": "2017", "Limited": "No", "Material": "Stainless Steel", "Bezel": "Rotating, 0-60 (Dive)", "Glass": "Hardlex", "Back": "Closed", "Shape": "Cushion", "Diameter": "45.00 mm", "Height": "13.50 mm", "Lug Width": "22.00 mm", "W/R": "200.00 m", "Color": "Blue", "Finish": "Sunburst", "Indexes": "Stick / Dot", "Hands": "Arrow"}, "image_url": "/watches/seiko/prospex-divers/srpc25.jpg", "image_url_source": "https://cdn.watchbase.com/watch/lg/seiko/prospex-divers/srpc25k1-64.jpg"}, {"slug": "sbdx017", "url": "/seiko/prospex-divers/sbdx017", "collection": "Prospex Divers watches62", "title": "Seiko - SBDX017 Prospex Diver Marinemaster 300 Stainless Steel / Black / Bracelet", "specs": {"Brand": "Seiko", "Family": "Prospex Divers", "Reference": "SBDX017 (aka: MM300)", "Name": "Prospex Diver Marinemaster 300 Stainless Steel / Black / Bracelet", "Movement": "Seiko caliber 8L35 Hours, Minutes, Seconds | Date", "Produced": "2015", "Limited": "No", "Material": "Stainless Steel", "Coating": "Dia-Shield", "Bezel": "Rotating, 0-60 (Dive)", "Glass": "Sapphire", "Back": "Closed", "Shape": "Round", "Diameter": "44.30 mm", "Height": "14.60 mm", "Lug Width": "20.00 mm", "W/R": "200.00 m", "Color": "Black", "Finish": "Matte", "Indexes": "Stick / Dot", "Hands": "Stick"}, "image_url": "/watches/seiko/prospex-divers/sbdx017.jpg", "image_url_source": "https://cdn.watchbase.com/watch/lg/seiko/prospex-divers/sbdx017-13.png"}, {"slug": "sbbn035", "url": "/seiko/prospex-divers/sbbn035", "collection": "Prospex Divers watches62", "title": "Seiko - SBBN035 Seiko Prospex Divers Marinemaster 300 Ninja Tuna", "specs": {"Brand": "Seiko", "Family": "Prospex Divers", "Reference": "SBBN035", "Name": "Seiko Prospex Divers Marinemaster 300 Ninja Tuna", "Movement": "Seiko caliber 7C46", "Produced": "2015", "Limited": "No", "Material": "Stainless Steel", "Coating": "PVD", "Bezel": "Rotating, 0-60 (Dive)", "Glass": "Sapphire", "Back": "Closed", "Shape": "Round", "Diameter": "47.70 mm", "Height": "14.70 mm", "Lug Width": "21.50 mm", "W/R": "300.00 m", "Nickname": "Ninja Tuna", "Color": "Black", "Finish": "Matte", "Indexes": "Stick / Dot", "Hands": "Arrow"}, "image_url": "/watches/seiko/prospex-divers/sbbn035.jpg", "image_url_source": "https://cdn.watchbase.com/watch/lg/seiko/prospex-divers/sbbn035-9c.png"}, {"slug": "spb153", "url": "/seiko/prospex-divers/spb153", "collection": "Prospex Divers watches62", "title": "Seiko - SPB153 Prospex Diver 1970 Stainless Steel / Green", "specs": {"Brand": "Seiko", "Family": "Prospex Divers", "Reference": "SPB153", "Name": "Prospex Diver 1970 Stainless Steel / Green", "Movement": "Seiko caliber 6R35 Hours, Minutes, Seconds | Date", "Produced": "2020", "Limited": "No", "Material": "Stainless Steel", "Bezel": "Rotating, 0-60 (Dive)", "Glass": "Sapphire", "Back": "Closed", "Shape": "Round", "Diameter": "42.70 mm", "Height": "13.20 mm", "Lug Width": "20.00 mm", "W/R": "200.00 m", "Color": "Green", "Finish": "Sunburst", "Indexes": "Stick / Dot", "Hands": "Stick"}, "image_url": "/watches/seiko/prospex-divers/spb153.jpg", "image_url_source": "https://cdn.watchbase.com/watch/lg/seiko/prospex-divers/spb153-60.jpg"}, {"slug": "sla017j1", "url": "/seiko/prospex-divers/sla017j1", "collection": "Prospex Divers watches62", "title": "Seiko - SLA017J1 Prospex Diver SLA017J1 Stainless Steel / Black", "specs": {"Brand": "Seiko", "Family": "Prospex Divers", "Reference": "SLA017J1 (aka: SLA017)", "Name": "Prospex Diver SLA017J1 Stainless Steel / Black", "Movement": "Seiko caliber 8L35 Hours, Minutes, Seconds | Date", "Produced": "2017 - 2017", "Limited": "Yes, 2000 units", "Material": "Stainless Steel", "Bezel": "Rotating, 0-60 (Dive)", "Glass": "Sapphire", "Back": "Closed", "Shape": "Round", "Diameter": "39.90 mm", "Lug Width": "19.00 mm", "W/R": "200.00 m", "Color": "Black", "Finish": "Matte", "Indexes": "Stick / Dot", "Hands": "Stick"}, "image_url": "/watches/seiko/prospex-divers/sla017j1.jpg", "image_url_source": "https://cdn.watchbase.com/watch/lg/seiko/prospex-divers/sla017j1-cc.jpg"}, {"slug": "sun021p1", "url": "/seiko/prospex-divers/sun021p1", "collection": "Prospex Divers watches62", "title": "Seiko - SUN021P1 Prospex Diver SUN021P1 Stainless Steel / Black", "specs": {"Brand": "Seiko", "Family": "Prospex Divers", "Reference": "SUN021P1", "Name": "Prospex Diver SUN021P1 Stainless Steel / Black", "Movement": "Seiko caliber 5M85 Additional 12 Hour Hand (adjustable), Hours, Minutes, Seconds | Date", "Limited": "No", "Material": "Stainless Steel", "Bezel": "Rotating, 0-60 (Dive)", "Glass": "Sapphire", "Back": "Closed", "Shape": "Round", "Diameter": "47.50 mm", "Lug Width": "24.00 mm", "W/R": "200.00 m", "Color": "Blue", "Finish": "Sunburst", "Indexes": "Stick / Dot", "Hands": "Arrow"}, "image_url": "/watches/seiko/prospex-divers/sun021p1.jpg", "image_url_source": "https://cdn.watchbase.com/watch/lg/seiko/prospex-divers/sun021p1-30.jpg"}, {"slug": "srp773", "url": "/seiko/prospex-divers/srp773", "collection": "Prospex Divers watches62", "title": "Seiko - SRP773 Prospex Diver Turtle Stainless Steel / Blue / Bracelet", "specs": {"Brand": "Seiko", "Family": "Prospex Divers", "Reference": "SRP773 (aka: SRP773K1)", "Name": "Prospex Diver Turtle Stainless Steel / Blue / Bracelet", "Movement": "Seiko caliber 4R36 Hours, Minutes, Seconds | Date, Day", "Produced": "2015", "Limited": "No", "Material": "Stainless Steel", "Bezel": "Rotating, 0-60 (Dive)", "Glass": "Hardlex", "Back": "Closed", "Shape": "Cushion", "Diameter": "45.00 mm", "Height": "13.50 mm", "Lug Width": "22.00 mm", "W/R": "200.00 m", "Color": "Blue", "Finish": "Matte", "Indexes": "Stick / Dot", "Hands": "Arrow"}, "image_url": "/watches/seiko/prospex-divers/srp773.jpg", "image_url_source": "https://cdn.watchbase.com/watch/lg/seiko/prospex-divers/srp773k1-ba.jpg"}, {"slug": "srpd03", "url": "/seiko/prospex-divers/srpd03", "collection": "Prospex Divers watches62", "title": "Seiko - SRPD03 Prospex Diver Samurai Stainless Steel / Dawn Grey", "specs": {"Brand": "Seiko", "Family": "Prospex Divers", "Reference": "SRPD03", "Name": "Prospex Diver Samurai Stainless Steel / Dawn Grey", "Movement": "Seiko caliber 4R35 Hours, Minutes, Seconds | Date", "Produced": "2018", "Limited": "Yes, 2018 units", "Material": "Stainless Steel", "Bezel": "Rotating, 0-60 (Dive)", "Glass": "Hardlex", "Back": "Closed", "Shape": "Round", "Diameter": "43.80 mm", "Lug Width": "22.00 mm", "W/R": "200.00 m", "Color": "Grey", "Finish": "Matte", "Indexes": "Stick / Dot", "Hands": "Arrow"}, "image_url": "/watches/seiko/prospex-divers/srpd03.jpg", "image_url_source": "https://cdn.watchbase.com/watch/lg/seiko/prospex-divers/srpd03-c5.jpg"}, {"slug": "spb051j1", "url": "/seiko/prospex-divers/spb051j1", "collection": "Prospex Divers watches62", "title": "Seiko - SPB051J1 Prospex Diver SPB051J1 Stainless Steel / Black", "specs": {"Brand": "Seiko", "Family": "Prospex Divers", "Reference": "SPB051J1", "Name": "Prospex Diver SPB051J1 Stainless Steel / Black", "Movement": "Seiko caliber 6R15 Hours, Minutes, Seconds | Date", "Produced": "2017", "Limited": "No", "Material": "Stainless Steel", "Bezel": "Rotating, 0-60 (Dive)", "Glass": "Sapphire", "Back": "Closed", "Shape": "Round", "Diameter": "42.60 mm", "Lug Width": "20.00 mm", "W/R": "200.00 m", "Color": "Black", "Finish": "Matte", "Indexes": "Stick / Dot", "Hands": "Arrow"}, "image_url": "/watches/seiko/prospex-divers/spb051j1.jpg", "image_url_source": "https://cdn.watchbase.com/watch/lg/seiko/prospex-divers/spb051j1-98.jpg"}, {"slug": "srpj51k1", "url": "/seiko/prospex-divers/srpj51k1", "collection": "Prospex Divers watches62", "title": "Seiko - SRPJ51K1 Prospex Diver Turtle Thong Sia Exclusive", "specs": {"Brand": "Seiko", "Family": "Prospex Divers", "Reference": "SRPJ51K1", "Name": "Prospex Diver Turtle Thong Sia Exclusive", "Movement": "Seiko caliber 4R36 Hours, Minutes, Seconds | Date, Day", "Produced": "2023", "Limited": "Yes, 1200 units", "Material": "Stainless Steel", "Bezel": "Rotating, 0-60 (Dive)", "Glass": "Hardlex", "Back": "Closed", "Shape": "Cushion", "Diameter": "45.00 mm", "Height": "13.50 mm", "Lug Width": "22.00 mm", "W/R": "200.00 m", "Color": "Green", "Finish": "Gradient", "Indexes": "Stick / Dot", "Hands": "Arrow"}, "image_url": "/watches/seiko/prospex-divers/srpj51k1.jpg", "image_url_source": "https://cdn.watchbase.com/watch/lg/seiko/prospex-divers/srpj51k1-d.jpg"}, {"slug": "ssc549p1", "url": "/seiko/prospex-divers/ssc549p1", "collection": "Prospex Divers watches62", "title": "Seiko - SSC549P1 Prospex Diver SSC549P1 Stainless Steel / Blue", "specs": {"Brand": "Seiko", "Family": "Prospex Divers", "Reference": "SSC549P1", "Name": "Prospex Diver SSC549P1 Stainless Steel / Blue", "Movement": "Seiko caliber 4R36 Hours, Minutes, Seconds | Date, Day", "Limited": "No", "Material": "Stainless Steel", "Glass": "Hardlex", "Back": "Closed", "Shape": "Round", "Diameter": "44.60 mm", "Lug Width": "22.00 mm", "W/R": "100.00 m", "Color": "Blue", "Indexes": "Stick / Dot", "Hands": "Dauphine"}, "image_url": "/watches/seiko/prospex-divers/ssc549p1.jpg", "image_url_source": "https://cdn.watchbase.com/watch/lg/seiko/prospex-divers/ssc549p1-be.jpg"}, {"slug": "ssc618p1", "url": "/seiko/prospex-divers/ssc618p1", "collection": "Prospex Divers watches62", "title": "Seiko - SSC618P1 Prospex Diver SSC618P1 Stainless Steel / Black", "specs": {"Brand": "Seiko", "Family": "Prospex Divers", "Reference": "SSC618P1", "Name": "Prospex Diver SSC618P1 Stainless Steel / Black", "Movement": "Seiko caliber V175 Hours, Minutes, Seconds | Chronograph | Solar Charging", "Produced": "2017", "Limited": "No", "Material": "Stainless Steel", "Coating": "PVD Gold", "Bezel": "Rotating, 0-60 (Dive)", "Glass": "Hardlex", "Back": "Closed", "Shape": "Round", "Diameter": "43.50 mm", "Lug Width": "22.00 mm", "W/R": "200.00 m", "Color": "Black", "Finish": "Matte", "Indexes": "Stick / Dot", "Hands": "Arrow"}, "image_url": "/watches/seiko/prospex-divers/ssc618p1.jpg", "image_url_source": "https://cdn.watchbase.com/watch/lg/seiko/prospex-divers/ssc618p1-7c.jpg"}, {"slug": "spb053j1", "url": "/seiko/prospex-divers/spb053j1", "collection": "Prospex Divers watches62", "title": "Seiko - SPB053J1 Prospex Diver SPB053J1 Stainless Steel / Blue", "specs": {"Brand": "Seiko", "Family": "Prospex Divers", "Reference": "SPB053J1", "Name": "Prospex Diver SPB053J1 Stainless Steel / Blue", "Movement": "Seiko caliber 6R15 Hours, Minutes, Seconds | Date", "Produced": "2017", "Limited": "No", "Material": "Stainless Steel", "Bezel": "Rotating, 0-60 (Dive)", "Glass": "Sapphire", "Back": "Closed", "Shape": "Round", "Diameter": "42.60 mm", "Lug Width": "20.00 mm", "W/R": "200.00 m", "Color": "Blue", "Finish": "Matte", "Indexes": "Stick / Dot", "Hands": "Arrow"}, "image_url": "/watches/seiko/prospex-divers/spb053j1.jpg", "image_url_source": "https://cdn.watchbase.com/watch/lg/seiko/prospex-divers/spb053j1-32.jpg"}, {"slug": "spb151", "url": "/seiko/prospex-divers/spb151", "collection": "Prospex Divers watches62", "title": "Seiko - SPB151 Prospex Diver 1970 Stainless Steel / Black / Bracelet", "specs": {"Brand": "Seiko", "Family": "Prospex Divers", "Reference": "SPB151", "Name": "Prospex Diver 1970 Stainless Steel / Black / Bracelet", "Movement": "Seiko caliber 6R35 Hours, Minutes, Seconds | Date", "Produced": "2020", "Limited": "No", "Material": "Stainless Steel", "Bezel": "Rotating, 0-60 (Dive)", "Glass": "Sapphire", "Back": "Closed", "Shape": "Round", "Diameter": "42.70 mm", "Height": "13.20 mm", "Lug Width": "20.00 mm", "W/R": "200.00 m", "Color": "Black", "Finish": "Matte", "Indexes": "Stick / Dot", "Hands": "Stick"}, "image_url": "/watches/seiko/prospex-divers/spb151.jpg", "image_url_source": "https://cdn.watchbase.com/watch/lg/seiko/prospex-divers/spb151-42.jpg"}, {"slug": "srpc49", "url": "/seiko/prospex-divers/srpc49", "collection": "Prospex Divers watches62", "title": "Seiko - SRPC49 Prospex Diver Turtle Stainless Steel / Black / Black Series", "specs": {"Brand": "Seiko", "Family": "Prospex Divers", "Reference": "SRPC49 (aka: SRPC49K1)", "Name": "Prospex Diver Turtle Stainless Steel / Black / Black Series", "Movement": "Seiko caliber 4R36 Hours, Minutes, Seconds | Date, Day", "Produced": "2017", "Limited": "No", "Material": "Stainless Steel", "Coating": "PVD", "Bezel": "Rotating, 0-60 (Dive)", "Glass": "Hardlex", "Back": "Closed", "Shape": "Cushion", "Diameter": "45.00 mm", "Height": "13.50 mm", "Lug Width": "22.00 mm", "W/R": "200.00 m", "Color": "Black", "Finish": "Matte", "Indexes": "Stick / Dot", "Hands": "Arrow"}, "image_url": "/watches/seiko/prospex-divers/srpc49.jpg", "image_url_source": "https://cdn.watchbase.com/watch/lg/seiko/prospex-divers/srpc49k1-97.jpg"}, {"slug": "srpc43", "url": "/seiko/prospex-divers/srpc43", "collection": "Prospex Divers watches62", "title": "Seiko - SRPC43 Prospex Diver Samurai Stainless Steel / Black / Bracelet / Zimbe", "specs": {"Brand": "Seiko", "Family": "Prospex Divers", "Reference": "SRPC43 (aka: SRPC43K1)", "Name": "Prospex Diver Samurai Stainless Steel / Black / Bracelet / Zimbe", "Movement": "Seiko caliber 4R35 Hours, Minutes, Seconds | Date", "Produced": "2017", "Limited": "No", "Material": "Stainless Steel", "Bezel": "Rotating, 0-60 (Dive)", "Glass": "Hardlex", "Back": "Closed", "Shape": "Round", "Diameter": "43.80 mm", "Lug Width": "22.00 mm", "W/R": "200.00 m", "Color": "Black", "Finish": "Matte", "Indexes": "Stick / Dot", "Hands": "Arrow"}, "image_url": "/watches/seiko/prospex-divers/srpc43.jpg", "image_url_source": "https://cdn.watchbase.com/watch/lg/seiko/prospex-divers/srpc43-fd.jpg"}, {"slug": "sbdc047", "url": "/seiko/prospex-divers/sbdc047", "collection": "Prospex Divers watches62", "title": "Seiko - SBDC047 Prospex Diver Trans Ocean Stainless Steel / Blue / Bracelet", "specs": {"Brand": "Seiko", "Family": "Prospex Divers", "Reference": "SBDC047", "Name": "Prospex Diver Trans Ocean Stainless Steel / Blue / Bracelet", "Movement": "Seiko caliber 6R15 Hours, Minutes, Seconds | Date", "Produced": "2016", "Limited": "No", "Material": "Stainless Steel", "Coating": "Dia-Shield", "Bezel": "Rotating, 0-60 (Dive)", "Glass": "Sapphire", "Back": "Closed", "Shape": "Round", "Diameter": "45.00 mm", "Height": "13.80 mm", "W/R": "200.00 m", "Color": "Blue", "Finish": "Matte", "Indexes": "Stick / Dot", "Hands": "Arrow"}, "image_url": "/watches/seiko/prospex-divers/sbdc047.jpg", "image_url_source": "https://cdn.watchbase.com/watch/lg/seiko/prospex-divers/sbdc047-27.png"}, {"slug": "srpc44", "url": "/seiko/prospex-divers/srpc44", "collection": "Prospex Divers watches62", "title": "Seiko - SRPC44 Prospex Diver Turtle Goldtone / Black / Rubber", "specs": {"Brand": "Seiko", "Family": "Prospex Divers", "Reference": "SRPC44", "Name": "Prospex Diver Turtle Goldtone / Black / Rubber", "Movement": "Seiko caliber 4R36 Hours, Minutes, Seconds | Date, Day", "Produced": "2018", "Limited": "No", "Material": "Stainless Steel", "Coating": "PVD Gold", "Bezel": "Rotating, 0-60 (Dive)", "Glass": "Hardlex", "Back": "Closed", "Shape": "Cushion", "Diameter": "45.00 mm", "Height": "13.50 mm", "Lug Width": "22.00 mm", "W/R": "200.00 m", "Color": "Black", "Finish": "Sunburst", "Indexes": "Stick / Dot", "Hands": "Arrow"}, "image_url": "/watches/seiko/prospex-divers/srpc44.jpg", "image_url_source": "https://cdn.watchbase.com/watch/lg/seiko/prospex-divers/srpc44-3b.jpg"}, {"slug": "ssc617p1", "url": "/seiko/prospex-divers/ssc617p1", "collection": "Prospex Divers watches62", "title": "Seiko - SSC617P1 Prospex Diver SSC617P1 Stainless Steel / Black", "specs": {"Brand": "Seiko", "Family": "Prospex Divers", "Reference": "SSC617P1", "Name": "Prospex Diver SSC617P1 Stainless Steel / Black", "Movement": "Seiko caliber V175 Hours, Minutes, Seconds | Chronograph | Solar Charging", "Produced": "2017", "Limited": "No", "Material": "Stainless Steel", "Bezel": "Rotating, 0-60 (Dive)", "Glass": "Hardlex", "Back": "Closed", "Shape": "Round", "Diameter": "43.50 mm", "Lug Width": "22.00 mm", "W/R": "200.00 m", "Color": "Black", "Finish": "Matte", "Indexes": "Stick / Dot", "Hands": "Arrow"}, "image_url": "/watches/seiko/prospex-divers/ssc617p1.jpg", "image_url_source": "https://cdn.watchbase.com/watch/lg/seiko/prospex-divers/ssc617p1-e1.jpg"}, {"slug": "sbdc039", "url": "/seiko/prospex-divers/sbdc039", "collection": "Prospex Divers watches62", "title": "Seiko - SBDC039 Prospex Diver Trans Ocean Stainless Steel / Black / Bracelet", "specs": {"Brand": "Seiko", "Family": "Prospex Divers", "Reference": "SBDC039", "Name": "Prospex Diver Trans Ocean Stainless Steel / Black / Bracelet", "Movement": "Seiko caliber 6R15 Hours, Minutes, Seconds | Date", "Produced": "2016", "Limited": "No", "Material": "Stainless Steel", "Bezel": "Rotating, 0-60 (Dive)", "Glass": "Sapphire", "Back": "Closed", "Shape": "Round", "Diameter": "45.00 mm", "Height": "13.80 mm", "W/R": "200.00 m", "Color": "Black", "Finish": "Matte", "Indexes": "Stick / Dot", "Hands": "Arrow"}, "image_url": "/watches/seiko/prospex-divers/sbdc039.jpg", "image_url_source": "https://cdn.watchbase.com/watch/lg/seiko/prospex-divers/sbdc039-5.png"}, {"slug": "srpb55", "url": "/seiko/prospex-divers/srpb55", "collection": "Prospex Divers watches62", "title": "Seiko - SRPB55 Prospex Diver Samurai Stainless Steel / Black / Rubber", "specs": {"Brand": "Seiko", "Family": "Prospex Divers", "Reference": "SRPB55 (aka: SRPB55K1)", "Name": "Prospex Diver Samurai Stainless Steel / Black / Rubber", "Movement": "Seiko caliber 4R35 Hours, Minutes, Seconds | Date", "Produced": "2017", "Limited": "No", "Material": "Stainless Steel", "Coating": "PVD", "Bezel": "Rotating, 0-60 (Dive)", "Glass": "Hardlex", "Back": "Closed", "Shape": "Round", "Diameter": "43.80 mm", "Lug Width": "22.00 mm", "W/R": "200.00 m", "Color": "Black", "Finish": "Matte", "Indexes": "Stick / Dot", "Hands": "Arrow"}, "image_url": "/watches/seiko/prospex-divers/srpb55.jpg", "image_url_source": "https://cdn.watchbase.com/watch/lg/seiko/prospex-divers/srpb55k1-26.jpg"}, {"slug": "srpb53", "url": "/seiko/prospex-divers/srpb53", "collection": "Prospex Divers watches62", "title": "Seiko - SRPB53 Prospex Diver Samurai Stainless Steel / Blue / Rubber", "specs": {"Brand": "Seiko", "Family": "Prospex Divers", "Reference": "SRPB53 (aka: SRPB53K1)", "Name": "Prospex Diver Samurai Stainless Steel / Blue / Rubber", "Movement": "Seiko caliber 4R35 Hours, Minutes, Seconds | Date", "Produced": "2017", "Limited": "No", "Material": "Stainless Steel", "Bezel": "Rotating, 0-60 (Dive)", "Glass": "Hardlex", "Back": "Closed", "Shape": "Round", "Diameter": "43.80 mm", "Lug Width": "22.00 mm", "W/R": "200.00 m", "Color": "Blue", "Finish": "Matte", "Indexes": "Stick / Dot", "Hands": "Arrow"}, "image_url": "/watches/seiko/prospex-divers/srpb53.jpg", "image_url_source": "https://cdn.watchbase.com/watch/lg/seiko/prospex-divers/srpb53k1-22.jpg"}, {"slug": "srpb51", "url": "/seiko/prospex-divers/srpb51", "collection": "Prospex Divers watches62", "title": "Seiko - SRPB51 Prospex Diver Samurai Stainless Steel / Black / Bracelet", "specs": {"Brand": "Seiko", "Family": "Prospex Divers", "Reference": "SRPB51 (aka: SRPB51K1)", "Name": "Prospex Diver Samurai Stainless Steel / Black / Bracelet", "Movement": "Seiko caliber 4R35 Hours, Minutes, Seconds | Date", "Produced": "2017", "Limited": "No", "Material": "Stainless Steel", "Bezel": "Rotating, 0-60 (Dive)", "Glass": "Hardlex", "Back": "Closed", "Shape": "Round", "Diameter": "43.80 mm", "Lug Width": "22.00 mm", "W/R": "200.00 m", "Color": "Black", "Finish": "Matte", "Indexes": "Stick / Dot", "Hands": "Arrow"}, "image_url": "/watches/seiko/prospex-divers/srpb51.jpg", "image_url_source": "https://cdn.watchbase.com/watch/lg/seiko/prospex-divers/srpb51k1-72.jpg"}, {"slug": "srp779", "url": "/seiko/prospex-divers/srp779", "collection": "Prospex Divers watches62", "title": "Seiko - SRP779 Prospex Diver Turtle Stainless Steel / Black / Rubber / Pepsi", "specs": {"Brand": "Seiko", "Family": "Prospex Divers", "Reference": "SRP779 (aka: SRP779K1)", "Name": "Prospex Diver Turtle Stainless Steel / Black / Rubber / Pepsi", "Movement": "Seiko caliber 4R36 Hours, Minutes, Seconds | Date, Day", "Produced": "2015", "Limited": "No", "Material": "Stainless Steel", "Bezel": "Rotating, 0-60 (Dive)", "Glass": "Hardlex", "Back": "Closed", "Shape": "Cushion", "Diameter": "45.00 mm", "Height": "13.50 mm", "Lug Width": "22.00 mm", "W/R": "200.00 m", "Color": "Black", "Finish": "Matte", "Indexes": "Stick / Dot", "Hands": "Arrow"}, "image_url": "/watches/seiko/prospex-divers/srp779.jpg", "image_url_source": "https://cdn.watchbase.com/watch/lg/seiko/prospex-divers/srp779k1-e2.jpg"}, {"slug": "srpb99", "url": "/seiko/prospex-divers/srpb99", "collection": "Prospex Divers watches62", "title": "Seiko - SRPB99 Prospex Diver Samurai Stainless Steel / Black / Bracelet / Padi", "specs": {"Brand": "Seiko", "Family": "Prospex Divers", "Reference": "SRPB99 (aka: SRPB99J1)", "Name": "Prospex Diver Samurai Stainless Steel / Black / Bracelet / Padi", "Movement": "Seiko caliber 4R35 Hours, Minutes, Seconds | Date", "Produced": "2017", "Limited": "No", "Material": "Stainless Steel", "Bezel": "Rotating, 0-60 (Dive)", "Glass": "Hardlex", "Back": "Closed", "Shape": "Round", "Diameter": "43.80 mm", "Lug Width": "22.00 mm", "W/R": "200.00 m", "Color": "Black", "Finish": "Matte", "Indexes": "Stick / Dot", "Hands": "Arrow"}, "image_url": "/watches/seiko/prospex-divers/srpb99.jpg", "image_url_source": "https://cdn.watchbase.com/watch/lg/seiko/prospex-divers/srpb99-d7.jpg"}, {"slug": "spb301", "url": "/seiko/prospex-divers/spb301", "collection": "Prospex Divers watches62", "title": "Seiko - SPB301 Prospex Diver 1970 Save the Ocean", "specs": {"Brand": "Seiko", "Family": "Prospex Divers", "Reference": "SPB301", "Name": "Prospex Diver 1970 Save the Ocean", "Movement": "Seiko caliber 6R35 Hours, Minutes, Seconds | Date", "Produced": "2022", "Limited": "No", "Material": "Stainless Steel", "Bezel": "Rotating, 0-60 (Dive)", "Glass": "Sapphire", "Back": "Closed", "Shape": "Round", "Diameter": "42.70 mm", "Height": "13.20 mm", "Lug Width": "20.00 mm", "W/R": "200.00 m", "Color": "Silver", "Finish": "Matte", "Indexes": "Stick / Dot", "Hands": "Stick"}, "image_url": "/watches/seiko/prospex-divers/spb301.jpg", "image_url_source": "https://cdn.watchbase.com/watch/lg/seiko/prospex-divers/spb301-35.jpg"}, {"slug": "srp787", "url": "/seiko/prospex-divers/srp787", "collection": "Prospex Divers watches62", "title": "Seiko - SRP787 Prospex Diver Turtle Stainless Steel / Black / Bracelet / Batman", "specs": {"Brand": "Seiko", "Family": "Prospex Divers", "Reference": "SRP787 (aka: SRP787K1, Batman)", "Name": "Prospex Diver Turtle Stainless Steel / Black / Bracelet / Batman", "Movement": "Seiko caliber 4R36 Hours, Minutes, Seconds | Date, Day", "Produced": "2016", "Limited": "No", "Material": "Stainless Steel", "Bezel": "Rotating, 0-60 (Dive)", "Glass": "Hardlex", "Back": "Closed", "Shape": "Cushion", "Diameter": "45.00 mm", "Height": "13.50 mm", "Lug Width": "22.00 mm", "W/R": "200.00 m", "Color": "Blue", "Finish": "Matte", "Indexes": "Stick / Dot", "Hands": "Arrow"}, "image_url": "/watches/seiko/prospex-divers/srp787.jpg", "image_url_source": "https://cdn.watchbase.com/watch/lg/seiko/prospex-divers/srp787-89.jpg"}, {"slug": "srpa79k1", "url": "/seiko/prospex-divers/srpa79k1", "collection": "Prospex Divers watches62", "title": "Seiko - SRPA79K1 Prospex Diver SRPA79K1 Stainless Steel / Black", "specs": {"Brand": "Seiko", "Family": "Prospex Divers", "Reference": "SRPA79K1", "Name": "Prospex Diver SRPA79K1 Stainless Steel / Black", "Movement": "Seiko caliber 4R36 Hours, Minutes, Seconds | Date, Day", "Limited": "No", "Materials": "Ceramic, Stainless Steel", "Bezel": "Rotating, 0-60 (Dive)", "Glass": "Hardlex", "Back": "Closed", "Shape": "Round", "Diameter": "51.70 mm", "Lug Width": "22.00 mm", "W/R": "200.00 m", "Color": "Black", "Indexes": "Stick / Dot", "Hands": "Arrow"}, "image_url": "/watches/seiko/prospex-divers/srpa79k1.jpg", "image_url_source": "https://cdn.watchbase.com/watch/lg/seiko/prospex-divers/srpa79k1-8.jpg"}, {"slug": "srpb09", "url": "/seiko/prospex-divers/srpb09", "collection": "Prospex Divers watches62", "title": "Seiko - SRPB09 Prospex Diver Samurai Stainless Steel / Blue Lagoon / Bracelet", "specs": {"Brand": "Seiko", "Family": "Prospex Divers", "Reference": "SRPB09", "Name": "Prospex Diver Samurai Stainless Steel / Blue Lagoon / Bracelet", "Movement": "Seiko caliber 4R35 Hours, Minutes, Seconds | Date", "Produced": "2016", "Limited": "Yes, 6000 units", "Material": "Stainless Steel", "Bezel": "Rotating, 0-60 (Dive)", "Glass": "Hardlex", "Back": "Closed", "Shape": "Round", "Diameter": "43.80 mm", "Lug Width": "22.00 mm", "W/R": "200.00 m", "Color": "Blue", "Finish": "Sunburst", "Indexes": "Stick / Dot", "Hands": "Arrow"}, "image_url": "/watches/seiko/prospex-divers/srpb09.jpg", "image_url_source": "https://cdn.watchbase.com/watch/lg/seiko/prospex-divers/srpb09-5e.jpg"}, {"slug": "spb237", "url": "/seiko/prospex-divers/spb237", "collection": "Prospex Divers watches62", "title": "Seiko - SPB237 Prospex Diver 1970 Stainless Steel / Grey - Brown / NATO", "specs": {"Brand": "Seiko", "Family": "Prospex Divers", "Reference": "SPB237", "Name": "Prospex Diver 1970 Stainless Steel / Grey - Brown / NATO", "Movement": "Seiko caliber 6R35 Hours, Minutes, Seconds | Date", "Produced": "2021", "Limited": "No", "Material": "Stainless Steel", "Bezel": "Rotating, 0-60 (Dive)", "Glass": "Sapphire", "Back": "Closed", "Shape": "Round", "Diameter": "42.70 mm", "Height": "13.20 mm", "Lug Width": "20.00 mm", "W/R": "200.00 m", "Color": "Grey", "Finish": "Matte", "Indexes": "Stick / Dot", "Hands": "Stick"}, "image_url": "/watches/seiko/prospex-divers/spb237.jpg", "image_url_source": "https://cdn.watchbase.com/watch/lg/seiko/prospex-divers/spb237-1.jpg"}, {"slug": "spb183", "url": "/seiko/prospex-divers/spb183", "collection": "Prospex Divers watches62", "title": "Seiko - SPB183 Prospex Diver 1970 Stainless Steel / Blue / Bracelet", "specs": {"Brand": "Seiko", "Family": "Prospex Divers", "Reference": "SPB183", "Name": "Prospex Diver 1970 Stainless Steel / Blue / Bracelet", "Movement": "Seiko caliber 6R35 Hours, Minutes, Seconds | Date", "Produced": "2020", "Limited": "Yes, 5500 units", "Material": "Stainless Steel", "Bezel": "Rotating, 0-60 (Dive)", "Glass": "Sapphire", "Back": "Closed", "Shape": "Round", "Diameter": "42.70 mm", "Height": "13.20 mm", "Lug Width": "20.00 mm", "W/R": "200.00 m", "Color": "Green", "Finish": "Sunburst", "Indexes": "Stick / Dot", "Hands": "Stick"}, "image_url": "/watches/seiko/prospex-divers/spb183.jpg", "image_url_source": "https://cdn.watchbase.com/watch/lg/seiko/prospex-divers/spb183-35.jpg"}, {"slug": "srp775", "url": "/seiko/prospex-divers/srp775", "collection": "Prospex Divers watches62", "title": "Seiko - SRP775 Prospex Diver Turtle Stainless Steel / Black / Bracelet", "specs": {"Brand": "Seiko", "Family": "Prospex Divers", "Reference": "SRP775 (aka: SRP775K1)", "Name": "Prospex Diver Turtle Stainless Steel / Black / Bracelet", "Movement": "Seiko caliber 4R36 Hours, Minutes, Seconds | Date, Day", "Produced": "2015", "Limited": "No", "Material": "Stainless Steel", "Bezel": "Rotating, 0-60 (Dive)", "Glass": "Hardlex", "Back": "Closed", "Shape": "Cushion", "Diameter": "45.00 mm", "Height": "13.50 mm", "Lug Width": "22.00 mm", "W/R": "200.00 m", "Color": "Blue", "Finish": "Matte", "Indexes": "Stick / Dot", "Hands": "Arrow"}, "image_url": "/watches/seiko/prospex-divers/srp775.jpg", "image_url_source": "https://cdn.watchbase.com/watch/lg/seiko/prospex-divers/srp775k1-af.jpg"}, {"slug": "srpa21", "url": "/seiko/prospex-divers/srpa21", "collection": "Prospex Divers watches62", "title": "Seiko - SRPA21 Prospex Diver Turtle Stainless Steel / Blue / Bracelet / Padi", "specs": {"Brand": "Seiko", "Family": "Prospex Divers", "Reference": "SRPA21 (aka: SRPA21K1)", "Name": "Prospex Diver Turtle Stainless Steel / Blue / Bracelet / Padi", "Movement": "Seiko caliber 4R36 Hours, Minutes, Seconds | Date, Day", "Produced": "2016", "Limited": "No", "Material": "Stainless Steel", "Bezel": "Rotating, 0-60 (Dive)", "Glass": "Hardlex", "Back": "Closed", "Shape": "Cushion", "Diameter": "45.00 mm", "Height": "13.50 mm", "Lug Width": "22.00 mm", "W/R": "200.00 m", "Color": "Blue", "Finish": "Sunburst", "Indexes": "Stick / Dot", "Hands": "Arrow"}, "image_url": "/watches/seiko/prospex-divers/srpa21.jpg", "image_url_source": "https://cdn.watchbase.com/watch/lg/seiko/prospex-divers/srpa21k1-8.jpg"}, {"slug": "sun065p1", "url": "/seiko/prospex-divers/sun065p1", "collection": "Prospex Divers watches62", "title": "Seiko - SUN065P1 Prospex Diver SUN065P1 Stainless Steel / Blue", "specs": {"Brand": "Seiko", "Family": "Prospex Divers", "Reference": "SUN065P1", "Name": "Prospex Diver SUN065P1 Stainless Steel / Blue", "Movement": "Seiko caliber 5M85 Additional 12 Hour Hand (adjustable), Hours, Minutes, Seconds | Date", "Limited": "No", "Material": "Stainless Steel", "Bezel": "Rotating, 0-60 (Dive)", "Glass": "Sapphire", "Back": "Closed", "Shape": "Round", "Diameter": "47.50 mm", "Lug Width": "24.00 mm", "W/R": "200.00 m", "Color": "Blue", "Finish": "Sunburst", "Indexes": "Stick / Dot", "Hands": "Arrow"}, "image_url": "/watches/seiko/prospex-divers/sun065p1.jpg", "image_url_source": "https://cdn.watchbase.com/watch/lg/seiko/prospex-divers/sun065p1-8e.jpg"}, {"slug": "srpa81k1", "url": "/seiko/prospex-divers/srpa81k1", "collection": "Prospex Divers watches62", "title": "Seiko - SRPA81K1 Prospex Diver SRPA81K1 Stainless Steel / Black", "specs": {"Brand": "Seiko", "Family": "Prospex Divers", "Reference": "SRPA81K1", "Name": "Prospex Diver SRPA81K1 Stainless Steel / Black", "Movement": "Seiko caliber 4R36 Hours, Minutes, Seconds | Date, Day", "Limited": "No", "Materials": "Ceramic, Stainless Steel", "Bezel": "Rotating, 0-60 (Dive)", "Glass": "Hardlex", "Back": "Closed", "Shape": "Round", "Diameter": "51.70 mm", "Lug Width": "22.00 mm", "W/R": "200.00 m", "Color": "Black", "Indexes": "Stick / Dot", "Hands": "Arrow"}, "image_url": "/watches/seiko/prospex-divers/srpa81k1.jpg", "image_url_source": "https://cdn.watchbase.com/watch/lg/seiko/prospex-divers/srpa81k1-b6.jpg"}, {"slug": "srpa82k1", "url": "/seiko/prospex-divers/srpa82k1", "collection": "Prospex Divers watches62", "title": "Seiko - SRPA82K1 Prospex Diver SRPA82K1 Stainless Steel / Black", "specs": {"Brand": "Seiko", "Family": "Prospex Divers", "Reference": "SRPA82K1", "Name": "Prospex Diver SRPA82K1 Stainless Steel / Black", "Movement": "Seiko caliber 4R36 Hours, Minutes, Seconds | Date, Day", "Limited": "No", "Materials": "Ceramic, Stainless Steel", "Bezel": "Rotating, 0-60 (Dive)", "Glass": "Hardlex", "Back": "Closed", "Shape": "Round", "Diameter": "51.70 mm", "Lug Width": "22.00 mm", "W/R": "200.00 m", "Color": "Black", "Indexes": "Stick / Dot", "Hands": "Arrow"}, "image_url": "/watches/seiko/prospex-divers/srpa82k1.jpg", "image_url_source": "https://cdn.watchbase.com/watch/lg/seiko/prospex-divers/srpa82k1-3e.jpg"}, {"slug": "sne441p1", "url": "/seiko/prospex-divers/sne441p1", "collection": "Prospex Divers watches62", "title": "Seiko - SNE441P1 Prospex Diver SNE441P1 Stainless Steel / Black", "specs": {"Brand": "Seiko", "Family": "Prospex Divers", "Reference": "SNE441P1", "Name": "Prospex Diver SNE441P1 Stainless Steel / Black", "Movement": "Seiko caliber V157 Hours, Minutes, Seconds | Date, Day | Solar Charging", "Limited": "No", "Material": "Stainless Steel", "Bezel": "Rotating, 0-60 (Dive)", "Glass": "Hardlex", "Back": "Closed", "Shape": "Round", "Diameter": "43.50 mm", "Lug Width": "20.00 mm", "W/R": "200.00 m", "Color": "Black", "Indexes": "Stick / Dot", "Hands": "Arrow"}, "image_url": "/watches/seiko/prospex-divers/sne441p1.jpg", "image_url_source": "https://cdn.watchbase.com/watch/lg/seiko/prospex-divers/sne441p1-68.jpg"}, {"slug": "sun019p1", "url": "/seiko/prospex-divers/sun019p1", "collection": "Prospex Divers watches62", "title": "Seiko - SUN019P1 Prospex Diver SUN019P1 Stainless Steel / Black", "specs": {"Brand": "Seiko", "Family": "Prospex Divers", "Reference": "SUN019P1", "Name": "Prospex Diver SUN019P1 Stainless Steel / Black", "Movement": "Seiko caliber 5M85 Additional 12 Hour Hand (adjustable), Hours, Minutes, Seconds | Date", "Limited": "No", "Material": "Stainless Steel", "Bezel": "Rotating, 0-60 (Dive)", "Glass": "Sapphire", "Back": "Closed", "Shape": "Round", "Diameter": "47.50 mm", "Lug Width": "24.00 mm", "W/R": "200.00 m", "Color": "Blue", "Finish": "Sunburst", "Indexes": "Stick / Dot", "Hands": "Arrow"}, "image_url": "/watches/seiko/prospex-divers/sun019p1.jpg", "image_url_source": "https://cdn.watchbase.com/watch/lg/seiko/prospex-divers/sun019p1-57.jpg"}, {"slug": "srp777", "url": "/seiko/prospex-divers/srp777", "collection": "Prospex Divers watches62", "title": "Seiko - SRP777 Prospex Diver Turtle Stainless Steel / Black / Rubber", "specs": {"Brand": "Seiko", "Family": "Prospex Divers", "Reference": "SRP777 (aka: SRP777K1, Jackpot)", "Name": "Prospex Diver Turtle Stainless Steel / Black / Rubber", "Movement": "Seiko caliber 4R36 Hours, Minutes, Seconds | Date, Day", "Produced": "2015", "Limited": "No", "Material": "Stainless Steel", "Bezel": "Rotating, 0-60 (Dive)", "Glass": "Hardlex", "Back": "Closed", "Shape": "Cushion", "Diameter": "45.00 mm", "Height": "13.50 mm", "Lug Width": "22.00 mm", "W/R": "200.00 m", "Color": "Black", "Finish": "Matte", "Indexes": "Stick / Dot", "Hands": "Arrow"}, "image_url": "/watches/seiko/prospex-divers/srp777.jpg", "image_url_source": "https://cdn.watchbase.com/watch/lg/seiko/prospex-divers/srp777k1-48.jpg"}, {"slug": "spb288", "url": "/seiko/prospex-divers/spb288", "collection": "Prospex Divers watches62", "title": "Seiko - SPB288 Prospex Diver 1970 Mystic Lagoon", "specs": {"Brand": "Seiko", "Family": "Prospex Divers", "Reference": "SPB288", "Name": "Prospex Diver 1970 Mystic Lagoon", "Movement": "Seiko caliber 6R35 Hours, Minutes, Seconds | Date", "Produced": "2022", "Limited": "No", "Material": "Stainless Steel", "Bezel": "Rotating, 0-60 (Dive)", "Glass": "Sapphire", "Back": "Closed", "Shape": "Round", "Diameter": "42.70 mm", "Height": "13.20 mm", "Lug Width": "20.00 mm", "W/R": "200.00 m", "Color": "Blue", "Finish": "Matte", "Indexes": "Stick / Dot", "Hands": "Stick"}, "image_url": "/watches/seiko/prospex-divers/spb288.jpg", "image_url_source": "https://cdn.watchbase.com/watch/lg/seiko/prospex-divers/spb288-f5.jpg"}, {"slug": "sne435p1", "url": "/seiko/prospex-divers/sne435p1", "collection": "Prospex Divers watches62", "title": "Seiko - SNE435P1 Prospex Diver SNE435P1 Stainless Steel / Blue", "specs": {"Brand": "Seiko", "Family": "Prospex Divers", "Reference": "SNE435P1", "Name": "Prospex Diver SNE435P1 Stainless Steel / Blue", "Movement": "Seiko caliber V157 Hours, Minutes, Seconds | Date, Day | Solar Charging", "Limited": "No", "Material": "Stainless Steel", "Bezel": "Rotating, 0-60 (Dive)", "Glass": "Hardlex", "Back": "Closed", "Shape": "Round", "Diameter": "43.50 mm", "Lug Width": "20.00 mm", "W/R": "200.00 m", "Color": "Blue", "Indexes": "Stick / Dot", "Hands": "Arrow"}, "image_url": "/watches/seiko/prospex-divers/sne435p1.jpg", "image_url_source": "https://cdn.watchbase.com/watch/lg/seiko/prospex-divers/sne435p1-10.jpg"}, {"slug": "sne439p1", "url": "/seiko/prospex-divers/sne439p1", "collection": "Prospex Divers watches62", "title": "Seiko - SNE439P1 Prospex Diver SNE439P1 Stainless Steel / Black", "specs": {"Brand": "Seiko", "Family": "Prospex Divers", "Reference": "SNE439P1", "Name": "Prospex Diver SNE439P1 Stainless Steel / Black", "Movement": "Seiko caliber V157 Hours, Minutes, Seconds | Date, Day | Solar Charging", "Limited": "No", "Material": "Stainless Steel", "Bezel": "Rotating, 0-60 (Dive)", "Glass": "Hardlex", "Back": "Closed", "Shape": "Round", "Diameter": "43.50 mm", "Lug Width": "20.00 mm", "W/R": "200.00 m", "Color": "Black", "Indexes": "Stick / Dot", "Hands": "Arrow"}, "image_url": "/watches/seiko/prospex-divers/sne439p1.jpg", "image_url_source": "https://cdn.watchbase.com/watch/lg/seiko/prospex-divers/sne439p1-65.jpg"}, {"slug": "ssf001j1", "url": "/seiko/prospex-divers/ssf001j1", "collection": "Prospex Divers watches62", "title": "Seiko - SSF001J1 Prospex Diver SSF001J1 Titanium / Blue", "specs": {"Brand": "Seiko", "Family": "Prospex Divers", "Reference": "SSF001J1", "Name": "Prospex Diver SSF001J1 Titanium / Blue", "Movement": "Seiko caliber 8X53 Additional 12 Hour Hand (adjustable), Day / Night Indication, Hours, Minutes, Seconds, World Time | Date, Day, Perpetual Calendar | GPS", "Limited": "Yes, 1500 units", "Material": "Titanium", "Bezel": "Rotating, 0-60 (Dive)", "Glass": "Sapphire", "Back": "Closed", "Shape": "Round", "Diameter": "48.50 mm", "Lug Width": "24.00 mm", "W/R": "200.00 m", "Color": "Blue", "Indexes": "Stick / Dot", "Hands": "Arrow"}, "image_url": "/watches/seiko/prospex-divers/ssf001j1.jpg", "image_url_source": "https://cdn.watchbase.com/watch/lg/seiko/prospex-divers/ssf001j1-4d.jpg"}, {"slug": "spb257", "url": "/seiko/prospex-divers/spb257", "collection": "Prospex Divers watches62", "title": "Seiko - SPB257 Prospex Diver 1970 Scuba Black Series", "specs": {"Brand": "Seiko", "Family": "Prospex Divers", "Reference": "SPB257", "Name": "Prospex Diver 1970 Scuba Black Series", "Movement": "Seiko caliber 6R35 Hours, Minutes, Seconds | Date", "Produced": "2022", "Limited": "Yes, 500 units", "Material": "Stainless Steel", "Coating": "DLC", "Bezel": "Rotating, 0-60 (Dive)", "Glass": "Sapphire", "Back": "Closed", "Shape": "Round", "Diameter": "42.70 mm", "Height": "13.20 mm", "Lug Width": "20.00 mm", "W/R": "200.00 m", "Color": "Black", "Finish": "Matte", "Indexes": "Stick / Dot", "Hands": "Stick"}, "image_url": "/watches/seiko/prospex-divers/spb257.jpg", "image_url_source": "https://cdn.watchbase.com/watch/lg/seiko/prospex-divers/spb257-12.jpg"}, {"slug": "ssc487p1", "url": "/seiko/prospex-divers/ssc487p1", "collection": "Prospex Divers watches62", "title": "Seiko - SSC487P1 Prospex Diver SSC487P1 Stainless Steel / Black", "specs": {"Brand": "Seiko", "Family": "Prospex Divers", "Reference": "SSC487P1", "Name": "Prospex Diver SSC487P1 Stainless Steel / Black", "Movement": "Seiko caliber V195 Hours, Minutes, Seconds, World Time | Solar Charging", "Limited": "No", "Material": "Stainless Steel", "Glass": "Sapphire", "Back": "Closed", "Shape": "Round", "Diameter": "44.60 mm", "Lug Width": "20.00 mm", "W/R": "100.00 m", "Color": "Black", "Finish": "Sunburst", "Indexes": "Stick / Dot", "Hands": "Stick"}, "image_url": "/watches/seiko/prospex-divers/ssc487p1.jpg", "image_url_source": "https://cdn.watchbase.com/watch/lg/seiko/prospex-divers/ssc487p1-ed.jpg"}, {"slug": "ssc551p1", "url": "/seiko/prospex-divers/ssc551p1", "collection": "Prospex Divers watches62", "title": "Seiko - SSC551P1 Prospex Diver SSC551P1 Stainless Steel / Blue", "specs": {"Brand": "Seiko", "Family": "Prospex Divers", "Reference": "SSC551P1", "Name": "Prospex Diver SSC551P1 Stainless Steel / Blue", "Movement": "Seiko caliber V195 Hours, Minutes, Seconds, World Time | Solar Charging", "Limited": "No", "Material": "Stainless Steel", "Glass": "Hardlex", "Back": "Closed", "Shape": "Round", "Diameter": "44.60 mm", "Lug Width": "22.00 mm", "W/R": "100.00 m", "Color": "Blue", "Indexes": "Stick / Dot", "Hands": "Dauphine"}, "image_url": "/watches/seiko/prospex-divers/ssc551p1.jpg", "image_url_source": "https://cdn.watchbase.com/watch/lg/seiko/prospex-divers/ssc551p1-f6.jpg"}, {"slug": "ssc613p1", "url": "/seiko/prospex-divers/ssc613p1", "collection": "Prospex Divers watches62", "title": "Seiko - SSC613P1 Prospex Diver SSC613P1 Stainless Steel / Black", "specs": {"Brand": "Seiko", "Family": "Prospex Divers", "Reference": "SSC613P1", "Name": "Prospex Diver SSC613P1 Stainless Steel / Black", "Movement": "Seiko caliber V175 Hours, Minutes, Seconds | Chronograph | Solar Charging", "Produced": "2017", "Limited": "No", "Material": "Stainless Steel", "Bezel": "Rotating, 0-60 (Dive)", "Glass": "Hardlex", "Back": "Closed", "Shape": "Round", "Diameter": "43.50 mm", "Lug Width": "22.00 mm", "W/R": "200.00 m", "Color": "Black", "Finish": "Matte", "Indexes": "Stick / Dot", "Hands": "Arrow"}, "image_url": "/watches/seiko/prospex-divers/ssc613p1.jpg", "image_url_source": "https://cdn.watchbase.com/watch/lg/seiko/prospex-divers/ssc613p1-63.jpg"}, {"slug": "ssc615p1", "url": "/seiko/prospex-divers/ssc615p1", "collection": "Prospex Divers watches62", "title": "Seiko - SSC615P1 Prospex Diver SSC615P1 Stainless Steel / Black", "specs": {"Brand": "Seiko", "Family": "Prospex Divers", "Reference": "SSC615P1", "Name": "Prospex Diver SSC615P1 Stainless Steel / Black", "Movement": "Seiko caliber V175 Hours, Minutes, Seconds | Chronograph | Solar Charging", "Produced": "2017", "Limited": "No", "Material": "Stainless Steel", "Bezel": "Rotating, 0-60 (Dive)", "Glass": "Hardlex", "Back": "Closed", "Shape": "Round", "Diameter": "43.50 mm", "Lug Width": "22.00 mm", "W/R": "200.00 m", "Color": "Black", "Finish": "Matte", "Indexes": "Stick / Dot", "Hands": "Arrow"}, "image_url": "/watches/seiko/prospex-divers/ssc615p1.jpg", "image_url_source": "https://cdn.watchbase.com/watch/lg/seiko/prospex-divers/ssc615p1-b5.jpg"}, {"slug": "srpb11", "url": "/seiko/prospex-divers/srpb11", "collection": "Prospex Divers watches62", "title": "Seiko - SRPB11 Prospex Diver Turtle Stainless Steel / Blue Lagoon / Bracelet", "specs": {"Brand": "Seiko", "Family": "Prospex Divers", "Reference": "SRPB11", "Name": "Prospex Diver Turtle Stainless Steel / Blue Lagoon / Bracelet", "Movement": "Seiko caliber 4R36 Hours, Minutes, Seconds | Date, Day", "Produced": "2017", "Limited": "Yes, 6000 units", "Material": "Stainless Steel", "Bezel": "Rotating, 0-60 (Dive)", "Glass": "Hardlex", "Back": "Closed", "Shape": "Cushion", "Diameter": "45.00 mm", "Height": "13.50 mm", "Lug Width": "22.00 mm", "W/R": "200.00 m", "Color": "Blue", "Finish": "Sunburst", "Indexes": "Stick / Dot", "Hands": "Arrow"}, "image_url": "/watches/seiko/prospex-divers/srpb11.jpg", "image_url_source": "https://cdn.watchbase.com/watch/lg/seiko/prospex-divers/srpb11-a7.jpg"}, {"slug": "sbdc181", "url": "/seiko/prospex-divers/sbdc181", "collection": "Prospex Divers watches62", "title": "Seiko - SBDC181 Prospex Diver 1970 Scuba Helly Hansen", "specs": {"Brand": "Seiko", "Family": "Prospex Divers", "Reference": "SBDC181", "Name": "Prospex Diver 1970 Scuba Helly Hansen", "Movement": "Seiko caliber 6R35 Hours, Minutes, Seconds | Date", "Produced": "2022", "Limited": "Yes, 500 units", "Material": "Stainless Steel", "Coating": "DLC", "Bezel": "Rotating, 0-60 (Dive)", "Glass": "Sapphire", "Back": "Closed", "Shape": "Round", "Diameter": "42.70 mm", "Height": "13.20 mm", "Lug Width": "20.00 mm", "W/R": "200.00 m", "Color": "Black", "Finish": "Matte", "Indexes": "Stick / Dot", "Hands": "Stick"}, "image_url": "/watches/seiko/prospex-divers/sbdc181.jpg", "image_url_source": "https://cdn.watchbase.com/watch/lg/seiko/prospex-divers/sbdc181-d5.jpg"}, {"slug": "ssc485p1", "url": "/seiko/prospex-divers/ssc485p1", "collection": "Prospex Divers watches62", "title": "Seiko - SSC485P1 Prospex Diver SSC485P1 Stainless Steel / Blue", "specs": {"Brand": "Seiko", "Family": "Prospex Divers", "Reference": "SSC485P1", "Name": "Prospex Diver SSC485P1 Stainless Steel / Blue", "Movement": "Seiko caliber V195 Hours, Minutes, Seconds, World Time | Solar Charging", "Limited": "No", "Material": "Stainless Steel", "Glass": "Sapphire", "Back": "Closed", "Shape": "Round", "Diameter": "44.60 mm", "Lug Width": "20.00 mm", "W/R": "100.00 m", "Color": "White", "Finish": "Sunburst", "Indexes": "Stick / Dot", "Hands": "Stick"}, "image_url": "/watches/seiko/prospex-divers/ssc485p1.jpg", "image_url_source": "https://cdn.watchbase.com/watch/lg/seiko/prospex-divers/ssc485p1-8.jpg"}, {"slug": "sne437p1", "url": "/seiko/prospex-divers/sne437p1", "collection": "Prospex Divers watches62", "title": "Seiko - SNE437P1 Prospex Diver SNE437P1 Stainless Steel / Black", "specs": {"Brand": "Seiko", "Family": "Prospex Divers", "Reference": "SNE437P1", "Name": "Prospex Diver SNE437P1 Stainless Steel / Black", "Movement": "Seiko caliber V157 Hours, Minutes, Seconds | Date, Day | Solar Charging", "Limited": "No", "Material": "Stainless Steel", "Bezel": "Rotating, 0-60 (Dive)", "Glass": "Hardlex", "Back": "Closed", "Shape": "Round", "Diameter": "43.50 mm", "Lug Width": "20.00 mm", "W/R": "200.00 m", "Color": "Black", "Indexes": "Stick / Dot", "Hands": "Arrow"}, "image_url": "/watches/seiko/prospex-divers/sne437p1.jpg", "image_url_source": "https://cdn.watchbase.com/watch/lg/seiko/prospex-divers/sne437p1-f5.jpg"}, {"slug": "srpa83k1", "url": "/seiko/prospex-divers/srpa83k1", "collection": "Prospex Divers watches62", "title": "Seiko - SRPA83K1 Prospex Diver SRPA83K1 Stainless Steel / Blue", "specs": {"Brand": "Seiko", "Family": "Prospex Divers", "Reference": "SRPA83K1", "Name": "Prospex Diver SRPA83K1 Stainless Steel / Blue", "Movement": "Seiko caliber 4R36 Hours, Minutes, Seconds | Date, Day", "Limited": "No", "Materials": "Ceramic, Stainless Steel", "Bezel": "Rotating, 0-60 (Dive)", "Glass": "Hardlex", "Back": "Closed", "Shape": "Round", "Diameter": "51.70 mm", "Lug Width": "22.00 mm", "W/R": "200.00 m", "Color": "Blue", "Indexes": "Stick / Dot", "Hands": "Arrow"}, "image_url": "/watches/seiko/prospex-divers/srpa83k1.jpg", "image_url_source": "https://cdn.watchbase.com/watch/lg/seiko/prospex-divers/srpa83k1-d1.jpg"}]}