{"name": "Datejust 36 watches709", "slug": "datejust", "total": 709, "page": 14, "references": [{"slug": "126203-0023", "url": "/rolex/datejust/126203-0023", "collection": "Datejust 36 watches709", "title": "Rolex - 126203-0023 Datejust 36 Stainless Steel / Yellow Gold / Smooth / MOP Diamond / Jubilee", "specs": {"Brand": "Rolex", "Family": "Datejust 36", "Reference": "126203-0023", "Name": "Datejust 36 Stainless Steel / Yellow Gold / Smooth / MOP Diamond / Jubilee", "Movement": "Rolex caliber 3235 Hours, Minutes, Seconds | Date | Chronometer", "Produced": "2018", "Limited": "No", "Materials": "Yellow Gold, Stainless Steel", "Glass": "Sapphire", "Back": "Closed", "Shape": "Round", "Diameter": "36.00 mm", "Lug Width": "20.00 mm", "W/R": "100.00 m", "Color": "White", "Material": "Mother of Pearl", "Indexes": "Gem-Set Indexes", "Hands": "Stick"}, "image_url": "/watches/rolex/datejust/126203-0023.jpg", "image_url_source": "https://cdn.watchbase.com/watch/lg/rolex/datejust/126203-0023-99.png"}, {"slug": "126203-0024", "url": "/rolex/datejust/126203-0024", "collection": "Datejust 36 watches709", "title": "Rolex - 126203-0024 Datejust 36 Stainless Steel / Yellow Gold / Smooth / MOP Diamond / Oyster", "specs": {"Brand": "Rolex", "Family": "Datejust 36", "Reference": "126203-0024", "Name": "Datejust 36 Stainless Steel / Yellow Gold / Smooth / MOP Diamond / Oyster", "Movement": "Rolex caliber 3235 Hours, Minutes, Seconds | Date | Chronometer", "Produced": "2018", "Limited": "No", "Materials": "Yellow Gold, Stainless Steel", "Glass": "Sapphire", "Back": "Closed", "Shape": "Round", "Diameter": "36.00 mm", "Lug Width": "20.00 mm", "W/R": "100.00 m", "Color": "White", "Material": "Mother of Pearl", "Indexes": "Gem-Set Indexes", "Hands": "Stick"}, "image_url": "/watches/rolex/datejust/126203-0024.jpg", "image_url_source": "https://cdn.watchbase.com/watch/lg/rolex/datejust/126203-0024-74.png"}, {"slug": "126203-0029", "url": "/rolex/datejust/126203-0029", "collection": "Datejust 36 watches709", "title": "Rolex - 126203-0029 Datejust 36 Stainless Steel / Yellow Gold / Smooth / White Roman / Jubilee", "specs": {"Brand": "Rolex", "Family": "Datejust 36", "Reference": "126203-0029", "Name": "Datejust 36 Stainless Steel / Yellow Gold / Smooth / White Roman / Jubilee", "Movement": "Rolex caliber 3235 Hours, Minutes, Seconds | Date | Chronometer", "Produced": "2018", "Limited": "No", "Materials": "Yellow Gold, Stainless Steel", "Glass": "Sapphire", "Back": "Closed", "Shape": "Round", "Diameter": "36.00 mm", "Lug Width": "20.00 mm", "W/R": "100.00 m", "Color": "White", "Finish": "Gloss", "Indexes": "Roman Numerals", "Hands": "Stick"}, "image_url": "/watches/rolex/datejust/126203-0029.jpg", "image_url_source": "https://cdn.watchbase.com/watch/lg/rolex/datejust/126203-0029-14.png"}, {"slug": "126203-0031", "url": "/rolex/datejust/126203-0031", "collection": "Datejust 36 watches709", "title": "Rolex - 126203-0031 Datejust 36 Stainless Steel / Yellow Gold / Smooth / Silver Roman Diamond / Jubilee", "specs": {"Brand": "Rolex", "Family": "Datejust 36", "Reference": "126203-0031", "Name": "Datejust 36 Stainless Steel / Yellow Gold / Smooth / Silver Roman Diamond / Jubilee", "Movement": "Rolex caliber 3235 Hours, Minutes, Seconds | Date | Chronometer", "Produced": "2018", "Limited": "No", "Materials": "Yellow Gold, Stainless Steel", "Glass": "Sapphire", "Back": "Closed", "Shape": "Round", "Diameter": "36.00 mm", "Lug Width": "20.00 mm", "W/R": "100.00 m", "Nickname": "Diamond 6-9", "Color": "Silver", "Finish": "Sunburst", "Indexes": "Roman Numerals", "Hands": "Stick"}, "image_url": "/watches/rolex/datejust/126203-0031.jpg", "image_url_source": "https://cdn.watchbase.com/watch/lg/rolex/datejust/126203-0031-97.png"}, {"slug": "126201-0016", "url": "/rolex/datejust/126201-0016", "collection": "Datejust 36 watches709", "title": "Rolex - 126201-0016 Datejust 36 Stainless Steel / Everose / Smooth / White Roman / Oyster", "specs": {"Brand": "Rolex", "Family": "Datejust 36", "Reference": "126201-0016", "Name": "Datejust 36 Stainless Steel / Everose / Smooth / White Roman / Oyster", "Movement": "Rolex caliber 3235 Hours, Minutes, Seconds | Date | Chronometer", "Produced": "2018", "Limited": "No", "Materials": "Rose Gold, Stainless Steel", "Glass": "Sapphire", "Back": "Closed", "Shape": "Round", "Diameter": "36.00 mm", "Lug Width": "20.00 mm", "W/R": "100.00 m", "Color": "White", "Finish": "Gloss", "Indexes": "Roman Numerals", "Hands": "Stick"}, "image_url": "/watches/rolex/datejust/126201-0016.jpg", "image_url_source": "https://cdn.watchbase.com/watch/lg/rolex/datejust/126201-0016-36.png"}, {"slug": "126201-0021", "url": "/rolex/datejust/126201-0021", "collection": "Datejust 36 watches709", "title": "Rolex - 126201-0021 Datejust 36 Stainless Steel / Everose / Smooth / MOP Diamond / Jubilee", "specs": {"Brand": "Rolex", "Family": "Datejust 36", "Reference": "126201-0021", "Name": "Datejust 36 Stainless Steel / Everose / Smooth / MOP Diamond / Jubilee", "Movement": "Rolex caliber 3235 Hours, Minutes, Seconds | Date | Chronometer", "Produced": "2018", "Limited": "No", "Materials": "Rose Gold, Stainless Steel", "Glass": "Sapphire", "Back": "Closed", "Shape": "Round", "Diameter": "36.00 mm", "Lug Width": "20.00 mm", "W/R": "100.00 m", "Color": "White", "Material": "Mother of Pearl", "Finish": "Gloss", "Indexes": "Gem-Set Indexes", "Hands": "Stick"}, "image_url": "/watches/rolex/datejust/126201-0021.jpg", "image_url_source": "https://cdn.watchbase.com/watch/lg/rolex/datejust/126201-0021-fd.png"}, {"slug": "126201-0028", "url": "/rolex/datejust/126201-0028", "collection": "Datejust 36 watches709", "title": "Rolex - 126201-0028 Datejust 36 Stainless Steel / Everose / Smooth / Rose Roman Diamond / Oyster", "specs": {"Brand": "Rolex", "Family": "Datejust 36", "Reference": "126201-0028", "Name": "Datejust 36 Stainless Steel / Everose / Smooth / Rose Roman Diamond / Oyster", "Movement": "Rolex caliber 3235 Hours, Minutes, Seconds | Date | Chronometer", "Produced": "2018", "Limited": "No", "Materials": "Rose Gold, Stainless Steel", "Glass": "Sapphire", "Back": "Closed", "Shape": "Round", "Diameter": "36.00 mm", "Lug Width": "20.00 mm", "W/R": "100.00 m", "Nickname": "Diamond 6-9", "Color": "Rose", "Finish": "Sunburst", "Indexes": "Roman Numerals", "Hands": "Stick"}, "image_url": "/watches/rolex/datejust/126201-0028.jpg", "image_url_source": "https://cdn.watchbase.com/watch/lg/rolex/datejust/126201-0028-8b.png"}, {"slug": "126201-0026", "url": "/rolex/datejust/126201-0026", "collection": "Datejust 36 watches709", "title": "Rolex - 126201-0026 Datejust 36 Stainless Steel / Everose / Smooth / Chocolate Computer / Oyster", "specs": {"Brand": "Rolex", "Family": "Datejust 36", "Reference": "126201-0026", "Name": "Datejust 36 Stainless Steel / Everose / Smooth / Chocolate Computer / Oyster", "Movement": "Rolex caliber 3235 Hours, Minutes, Seconds | Date | Chronometer", "Produced": "2018", "Limited": "No", "Materials": "Rose Gold, Stainless Steel", "Glass": "Sapphire", "Back": "Closed", "Shape": "Round", "Diameter": "36.00 mm", "Lug Width": "20.00 mm", "W/R": "100.00 m", "Nickname": "Computer", "Color": "Brown", "Finish": "Guilloche", "Indexes": "Gem-Set Indexes", "Hands": "Stick"}, "image_url": "/watches/rolex/datejust/126201-0026.jpg", "image_url_source": "https://cdn.watchbase.com/watch/lg/rolex/datejust/126201-0026-f9.png"}, {"slug": "126201-0015", "url": "/rolex/datejust/126201-0015", "collection": "Datejust 36 watches709", "title": "Rolex - 126201-0015 Datejust 36 Stainless Steel / Everose / Smooth / White Roman / Jubilee", "specs": {"Brand": "Rolex", "Family": "Datejust 36", "Reference": "126201-0015", "Name": "Datejust 36 Stainless Steel / Everose / Smooth / White Roman / Jubilee", "Movement": "Rolex caliber 3235 Hours, Minutes, Seconds | Date | Chronometer", "Produced": "2018", "Limited": "No", "Materials": "Rose Gold, Stainless Steel", "Glass": "Sapphire", "Back": "Closed", "Shape": "Round", "Diameter": "36.00 mm", "Lug Width": "20.00 mm", "W/R": "100.00 m", "Color": "White", "Finish": "Gloss", "Indexes": "Roman Numerals", "Hands": "Stick"}, "image_url": "/watches/rolex/datejust/126201-0015.jpg", "image_url_source": "https://cdn.watchbase.com/watch/lg/rolex/datejust/126201-0015-ac.png"}, {"slug": "126201-0018", "url": "/rolex/datejust/126201-0018", "collection": "Datejust 36 watches709", "title": "Rolex - 126201-0018 Datejust 36 Stainless Steel / Everose / Smooth / White / Oyster", "specs": {"Brand": "Rolex", "Family": "Datejust 36", "Reference": "126201-0018", "Name": "Datejust 36 Stainless Steel / Everose / Smooth / White / Oyster", "Movement": "Rolex caliber 3235 Hours, Minutes, Seconds | Date | Chronometer", "Produced": "2018", "Limited": "No", "Materials": "Rose Gold, Stainless Steel", "Glass": "Sapphire", "Back": "Closed", "Shape": "Round", "Diameter": "36.00 mm", "Lug Width": "20.00 mm", "W/R": "100.00 m", "Color": "White", "Indexes": "Stick / Dot", "Hands": "Stick"}, "image_url": "/watches/rolex/datejust/126201-0018.jpg", "image_url_source": "https://cdn.watchbase.com/watch/lg/rolex/datejust/126201-0018-fb.png"}, {"slug": "126201-0019", "url": "/rolex/datejust/126201-0019", "collection": "Datejust 36 watches709", "title": "Rolex - 126201-0019 Datejust 36 Stainless Steel / Everose / Smooth / Black Diamond / Jubilee", "specs": {"Brand": "Rolex", "Family": "Datejust 36", "Reference": "126201-0019", "Name": "Datejust 36 Stainless Steel / Everose / Smooth / Black Diamond / Jubilee", "Movement": "Rolex caliber 3235 Hours, Minutes, Seconds | Date | Chronometer", "Produced": "2018", "Limited": "No", "Materials": "Rose Gold, Stainless Steel", "Glass": "Sapphire", "Back": "Closed", "Shape": "Round", "Diameter": "36.00 mm", "Lug Width": "20.00 mm", "W/R": "100.00 m", "Color": "Black", "Finish": "Sunburst", "Indexes": "Gem-Set Indexes", "Hands": "Stick"}, "image_url": "/watches/rolex/datejust/126201-0019.jpg", "image_url_source": "https://cdn.watchbase.com/watch/lg/rolex/datejust/126201-0019-c2.png"}, {"slug": "126201-0017", "url": "/rolex/datejust/126201-0017", "collection": "Datejust 36 watches709", "title": "Rolex - 126201-0017 Datejust 36 Stainless Steel / Everose / Smooth / White / Jubilee", "specs": {"Brand": "Rolex", "Family": "Datejust 36", "Reference": "126201-0017", "Name": "Datejust 36 Stainless Steel / Everose / Smooth / White / Jubilee", "Movement": "Rolex caliber 3235 Hours, Minutes, Seconds | Date | Chronometer", "Produced": "2018", "Limited": "No", "Materials": "Rose Gold, Stainless Steel", "Glass": "Sapphire", "Back": "Closed", "Shape": "Round", "Diameter": "36.00 mm", "Lug Width": "20.00 mm", "W/R": "100.00 m", "Color": "White", "Indexes": "Stick / Dot", "Hands": "Stick"}, "image_url": "/watches/rolex/datejust/126201-0017.jpg", "image_url_source": "https://cdn.watchbase.com/watch/lg/rolex/datejust/126201-0017-ad.png"}, {"slug": "126201-0023", "url": "/rolex/datejust/126201-0023", "collection": "Datejust 36 watches709", "title": "Rolex - 126201-0023 Datejust 36 Stainless Steel / Everose / Smooth / Slate Roman Diamond / Jubilee", "specs": {"Brand": "Rolex", "Family": "Datejust 36", "Reference": "126201-0023", "Name": "Datejust 36 Stainless Steel / Everose / Smooth / Slate Roman Diamond / Jubilee", "Movement": "Rolex caliber 3235 Hours, Minutes, Seconds | Date | Chronometer", "Produced": "2018", "Limited": "No", "Materials": "Rose Gold, Stainless Steel", "Glass": "Sapphire", "Back": "Closed", "Shape": "Round", "Diameter": "36.00 mm", "Lug Width": "20.00 mm", "W/R": "100.00 m", "Nickname": "Diamond 6-9 Dark Rhodium", "Color": "Grey", "Finish": "Sunburst", "Indexes": "Roman Numerals", "Hands": "Stick"}, "image_url": "/watches/rolex/datejust/126201-0023.jpg", "image_url_source": "https://cdn.watchbase.com/watch/lg/rolex/datejust/126201-0023-7d.png"}, {"slug": "126201-0024", "url": "/rolex/datejust/126201-0024", "collection": "Datejust 36 watches709", "title": "Rolex - 126201-0024 Datejust 36 Stainless Steel / Everose / Smooth / Slate Roman Diamond / Oyster", "specs": {"Brand": "Rolex", "Family": "Datejust 36", "Reference": "126201-0024", "Name": "Datejust 36 Stainless Steel / Everose / Smooth / Slate Roman Diamond / Oyster", "Movement": "Rolex caliber 3235 Hours, Minutes, Seconds | Date | Chronometer", "Produced": "2018", "Limited": "No", "Materials": "Rose Gold, Stainless Steel", "Glass": "Sapphire", "Back": "Closed", "Shape": "Round", "Diameter": "36.00 mm", "Lug Width": "20.00 mm", "W/R": "100.00 m", "Nickname": "Diamond 6-9 Dark Rhodium", "Color": "Grey", "Finish": "Sunburst", "Indexes": "Roman Numerals", "Hands": "Stick"}, "image_url": "/watches/rolex/datejust/126201-0024.jpg", "image_url_source": "https://cdn.watchbase.com/watch/lg/rolex/datejust/126201-0024-2b.png"}, {"slug": "126283rbr-0002", "url": "/rolex/datejust/126283rbr-0002", "collection": "Datejust 36 watches709", "title": "Rolex - 126283RBR-0002 Datejust 36 Stainless Steel / Yellow Gold / Diamond / Champagne / Oyster", "specs": {"Brand": "Rolex", "Family": "Datejust 36", "Reference": "126283RBR-0002", "Name": "Datejust 36 Stainless Steel / Yellow Gold / Diamond / Champagne / Oyster", "Movement": "Rolex caliber 3235 Hours, Minutes, Seconds | Date | Chronometer", "Produced": "2018", "Limited": "No", "Materials": "Yellow Gold, Stainless Steel", "Bezel": "Gem-Set", "Glass": "Sapphire", "Back": "Closed", "Shape": "Round", "Diameter": "36.00 mm", "Lug Width": "20.00 mm", "W/R": "100.00 m", "Color": "Champagne", "Finish": "Sunburst", "Indexes": "Stick / Dot", "Hands": "Stick"}, "image_url": "/watches/rolex/datejust/126283rbr-0002.jpg", "image_url_source": "https://cdn.watchbase.com/watch/lg/rolex/datejust/126283rbr-0002-f3.png"}, {"slug": "126283rbr-0004", "url": "/rolex/datejust/126283rbr-0004", "collection": "Datejust 36 watches709", "title": "Rolex - 126283RBR-0004 Datejust 36 Stainless Steel / Yellow Gold / Diamond / Champagne Diamond / Oyster", "specs": {"Brand": "Rolex", "Family": "Datejust 36", "Reference": "126283RBR-0004", "Name": "Datejust 36 Stainless Steel / Yellow Gold / Diamond / Champagne Diamond / Oyster", "Movement": "Rolex caliber 3235 Hours, Minutes, Seconds | Date | Chronometer", "Produced": "2018", "Limited": "No", "Materials": "Yellow Gold, Stainless Steel", "Bezel": "Gem-Set", "Glass": "Sapphire", "Back": "Closed", "Shape": "Round", "Diameter": "36.00 mm", "Lug Width": "20.00 mm", "W/R": "100.00 m", "Color": "Champagne", "Finish": "Sunburst", "Indexes": "Gem-Set Indexes", "Hands": "Stick"}, "image_url": "/watches/rolex/datejust/126283rbr-0004.jpg", "image_url_source": "https://cdn.watchbase.com/watch/lg/rolex/datejust/126283rbr-0004-cb.png"}, {"slug": "126283rbr-0006", "url": "/rolex/datejust/126283rbr-0006", "collection": "Datejust 36 watches709", "title": "Rolex - 126283RBR-0006 Datejust 36 Stainless Steel / Yellow Gold / Diamond / White / Oyster", "specs": {"Brand": "Rolex", "Family": "Datejust 36", "Reference": "126283RBR-0006", "Name": "Datejust 36 Stainless Steel / Yellow Gold / Diamond / White / Oyster", "Movement": "Rolex caliber 3235 Hours, Minutes, Seconds | Date | Chronometer", "Produced": "2018", "Limited": "No", "Materials": "Yellow Gold, Stainless Steel", "Bezel": "Gem-Set", "Glass": "Sapphire", "Back": "Closed", "Shape": "Round", "Diameter": "36.00 mm", "Lug Width": "20.00 mm", "W/R": "100.00 m", "Color": "White", "Indexes": "Stick / Dot", "Hands": "Stick"}, "image_url": "/watches/rolex/datejust/126283rbr-0006.jpg", "image_url_source": "https://cdn.watchbase.com/watch/lg/rolex/datejust/126283rbr-0006-8e.png"}, {"slug": "126283rbr-0008", "url": "/rolex/datejust/126283rbr-0008", "collection": "Datejust 36 watches709", "title": "Rolex - 126283RBR-0008 Datejust 36 Stainless Steel / Yellow Gold / Diamond / Black Diamond / Oyster", "specs": {"Brand": "Rolex", "Family": "Datejust 36", "Reference": "126283RBR-0008", "Name": "Datejust 36 Stainless Steel / Yellow Gold / Diamond / Black Diamond / Oyster", "Movement": "Rolex caliber 3235 Hours, Minutes, Seconds | Date | Chronometer", "Produced": "2018", "Limited": "No", "Materials": "Yellow Gold, Stainless Steel", "Bezel": "Gem-Set", "Glass": "Sapphire", "Back": "Closed", "Shape": "Round", "Diameter": "36.00 mm", "Lug Width": "20.00 mm", "W/R": "100.00 m", "Color": "Black", "Indexes": "Gem-Set Indexes", "Hands": "Stick"}, "image_url": "/watches/rolex/datejust/126283rbr-0008.jpg", "image_url_source": "https://cdn.watchbase.com/watch/lg/rolex/datejust/126283rbr-0008-bb.png"}, {"slug": "126283rbr-0011", "url": "/rolex/datejust/126283rbr-0011", "collection": "Datejust 36 watches709", "title": "Rolex - 126283RBR-0011 Datejust 36 Stainless Steel / Yellow Gold / Diamond / Olive Green Roman Diamond / Jubilee", "specs": {"Brand": "Rolex", "Family": "Datejust 36", "Reference": "126283RBR-0011", "Name": "Datejust 36 Stainless Steel / Yellow Gold / Diamond / Olive Green Roman Diamond / Jubilee", "Movement": "Rolex caliber 3235 Hours, Minutes, Seconds | Date | Chronometer", "Produced": "2018", "Limited": "No", "Materials": "Yellow Gold, Stainless Steel", "Bezel": "Gem-Set", "Glass": "Sapphire", "Back": "Closed", "Shape": "Round", "Diameter": "36.00 mm", "Lug Width": "20.00 mm", "W/R": "100.00 m", "Nickname": "Diamond 6-9 Olive", "Color": "Green", "Finish": "Sunburst", "Indexes": "Roman Numerals", "Hands": "Stick"}, "image_url": "/watches/rolex/datejust/126283rbr-0011.jpg", "image_url_source": "https://cdn.watchbase.com/watch/lg/rolex/datejust/126283rbr-0011-30.png"}, {"slug": "126283rbr-0015", "url": "/rolex/datejust/126283rbr-0015", "collection": "Datejust 36 watches709", "title": "Rolex - 126283RBR-0015 Datejust 36 Stainless Steel / Yellow Gold / Diamond / White Roman / Jubilee", "specs": {"Brand": "Rolex", "Family": "Datejust 36", "Reference": "126283RBR-0015", "Name": "Datejust 36 Stainless Steel / Yellow Gold / Diamond / White Roman / Jubilee", "Movement": "Rolex caliber 3235 Hours, Minutes, Seconds | Date | Chronometer", "Produced": "2018", "Limited": "No", "Materials": "Yellow Gold, Stainless Steel", "Bezel": "Gem-Set", "Glass": "Sapphire", "Back": "Closed", "Shape": "Round", "Diameter": "36.00 mm", "Lug Width": "20.00 mm", "W/R": "100.00 m", "Color": "White", "Finish": "Gloss", "Indexes": "Roman Numerals", "Hands": "Stick"}, "image_url": "/watches/rolex/datejust/126283rbr-0015.jpg", "image_url_source": "https://cdn.watchbase.com/watch/lg/rolex/datejust/126283rbr-0015-2f.png"}, {"slug": "126283rbr-0016", "url": "/rolex/datejust/126283rbr-0016", "collection": "Datejust 36 watches709", "title": "Rolex - 126283RBR-0016 Datejust 36 Stainless Steel / Yellow Gold / Diamond / White Roman / Oyster", "specs": {"Brand": "Rolex", "Family": "Datejust 36", "Reference": "126283RBR-0016", "Name": "Datejust 36 Stainless Steel / Yellow Gold / Diamond / White Roman / Oyster", "Movement": "Rolex caliber 3235 Hours, Minutes, Seconds | Date | Chronometer", "Produced": "2018", "Limited": "No", "Materials": "Yellow Gold, Stainless Steel", "Bezel": "Gem-Set", "Glass": "Sapphire", "Back": "Closed", "Shape": "Round", "Diameter": "36.00 mm", "Lug Width": "20.00 mm", "W/R": "100.00 m", "Color": "White", "Finish": "Gloss", "Indexes": "Roman Numerals", "Hands": "Stick"}, "image_url": "/watches/rolex/datejust/126283rbr-0016.jpg", "image_url_source": "https://cdn.watchbase.com/watch/lg/rolex/datejust/126283rbr-0016-b9.png"}, {"slug": "126283rbr-0018", "url": "/rolex/datejust/126283rbr-0018", "collection": "Datejust 36 watches709", "title": "Rolex - 126283RBR-0018 Datejust 36 Stainless Steel / Yellow Gold / Diamond / Silver Roman Diamond / Oyster", "specs": {"Brand": "Rolex", "Family": "Datejust 36", "Reference": "126283RBR-0018", "Name": "Datejust 36 Stainless Steel / Yellow Gold / Diamond / Silver Roman Diamond / Oyster", "Movement": "Rolex caliber 3235 Hours, Minutes, Seconds | Date | Chronometer", "Produced": "2018", "Limited": "No", "Materials": "Yellow Gold, Stainless Steel", "Bezel": "Gem-Set", "Glass": "Sapphire", "Back": "Closed", "Shape": "Round", "Diameter": "36.00 mm", "Lug Width": "20.00 mm", "W/R": "100.00 m", "Nickname": "Diamond 6-9", "Color": "Silver", "Finish": "Sunburst", "Indexes": "Roman Numerals", "Hands": "Stick"}, "image_url": "/watches/rolex/datejust/126283rbr-0018.jpg", "image_url_source": "https://cdn.watchbase.com/watch/lg/rolex/datejust/126283rbr-0018-6d.png"}, {"slug": "126281rbr-0008", "url": "/rolex/datejust/126281rbr-0008", "collection": "Datejust 36 watches709", "title": "Rolex - 126281RBR-0008 Datejust 36 Stainless Steel / Everose / Diamond / Black Diamond / Oyster", "specs": {"Brand": "Rolex", "Family": "Datejust 36", "Reference": "126281RBR-0008", "Name": "Datejust 36 Stainless Steel / Everose / Diamond / Black Diamond / Oyster", "Movement": "Rolex caliber 3235 Hours, Minutes, Seconds | Date | Chronometer", "Produced": "2018", "Limited": "No", "Materials": "Rose Gold, Stainless Steel", "Bezel": "Gem-Set", "Glass": "Sapphire", "Back": "Closed", "Shape": "Round", "Diameter": "36.00 mm", "Lug Width": "20.00 mm", "W/R": "100.00 m", "Color": "Black", "Finish": "Sunburst", "Indexes": "Gem-Set Indexes", "Hands": "Stick"}, "image_url": "/watches/rolex/datejust/126281rbr-0008.jpg", "image_url_source": "https://cdn.watchbase.com/watch/lg/rolex/datejust/126281rbr-0008-6.png"}, {"slug": "126281rbr-0002", "url": "/rolex/datejust/126281rbr-0002", "collection": "Datejust 36 watches709", "title": "Rolex - 126281RBR-0002 Datejust 36 Stainless Steel / Everose / Diamond / Slate / Oyster", "specs": {"Brand": "Rolex", "Family": "Datejust 36", "Reference": "126281RBR-0002", "Name": "Datejust 36 Stainless Steel / Everose / Diamond / Slate / Oyster", "Movement": "Rolex caliber 3235 Hours, Minutes, Seconds | Date | Chronometer", "Produced": "2018", "Limited": "No", "Materials": "Rose Gold, Stainless Steel", "Bezel": "Gem-Set", "Glass": "Sapphire", "Back": "Closed", "Shape": "Round", "Diameter": "36.00 mm", "Lug Width": "20.00 mm", "W/R": "100.00 m", "Nickname": "Dark Rhodium", "Color": "Grey", "Finish": "Sunburst", "Indexes": "Stick / Dot", "Hands": "Stick"}, "image_url": "/watches/rolex/datejust/126281rbr-0002.jpg", "image_url_source": "https://cdn.watchbase.com/watch/lg/rolex/datejust/126281rbr-0002-f8.png"}, {"slug": "126281rbr-0004", "url": "/rolex/datejust/126281rbr-0004", "collection": "Datejust 36 watches709", "title": "Rolex - 126281RBR-0004 Datejust 36 Stainless Steel / Everose / Diamond / White Roman / Oyster", "specs": {"Brand": "Rolex", "Family": "Datejust 36", "Reference": "126281RBR-0004", "Name": "Datejust 36 Stainless Steel / Everose / Diamond / White Roman / Oyster", "Movement": "Rolex caliber 3235 Hours, Minutes, Seconds | Date | Chronometer", "Produced": "2018", "Limited": "No", "Materials": "Rose Gold, Stainless Steel", "Bezel": "Gem-Set", "Glass": "Sapphire", "Back": "Closed", "Shape": "Round", "Diameter": "36.00 mm", "Lug Width": "20.00 mm", "W/R": "100.00 m", "Color": "White", "Finish": "Gloss", "Indexes": "Roman Numerals", "Hands": "Stick"}, "image_url": "/watches/rolex/datejust/126281rbr-0004.jpg", "image_url_source": "https://cdn.watchbase.com/watch/lg/rolex/datejust/126281rbr-0004-b8.png"}, {"slug": "126281rbr-0016", "url": "/rolex/datejust/126281rbr-0016", "collection": "Datejust 36 watches709", "title": "Rolex - 126281RBR-0016 Datejust 36 Stainless Steel / Everose / Diamond / Rose Roman Diamond / Oyster", "specs": {"Brand": "Rolex", "Family": "Datejust 36", "Reference": "126281RBR-0016", "Name": "Datejust 36 Stainless Steel / Everose / Diamond / Rose Roman Diamond / Oyster", "Movement": "Rolex caliber 3235 Hours, Minutes, Seconds | Date | Chronometer", "Produced": "2018", "Limited": "No", "Materials": "Rose Gold, Stainless Steel", "Bezel": "Gem-Set", "Glass": "Sapphire", "Back": "Closed", "Shape": "Round", "Diameter": "36.00 mm", "Lug Width": "20.00 mm", "W/R": "100.00 m", "Nickname": "Diamond 6-9", "Color": "Rose", "Finish": "Sunburst", "Indexes": "Roman Numerals", "Hands": "Stick"}, "image_url": "/watches/rolex/datejust/126281rbr-0016.jpg", "image_url_source": "https://cdn.watchbase.com/watch/lg/rolex/datejust/126281rbr-0016-46.png"}, {"slug": "126281rbr-0007", "url": "/rolex/datejust/126281rbr-0007", "collection": "Datejust 36 watches709", "title": "Rolex - 126281RBR-0007 Datejust 36 Stainless Steel / Everose / Diamond / Black Diamond / Jubilee", "specs": {"Brand": "Rolex", "Family": "Datejust 36", "Reference": "126281RBR-0007", "Name": "Datejust 36 Stainless Steel / Everose / Diamond / Black Diamond / Jubilee", "Movement": "Rolex caliber 3235 Hours, Minutes, Seconds | Date | Chronometer", "Produced": "2018", "Limited": "No", "Materials": "Rose Gold, Stainless Steel", "Bezel": "Gem-Set", "Glass": "Sapphire", "Back": "Closed", "Shape": "Round", "Diameter": "36.00 mm", "Lug Width": "20.00 mm", "W/R": "100.00 m", "Color": "Black", "Finish": "Sunburst", "Indexes": "Gem-Set Indexes", "Hands": "Stick"}, "image_url": "/watches/rolex/datejust/126281rbr-0007.jpg", "image_url_source": "https://cdn.watchbase.com/watch/lg/rolex/datejust/126281rbr-0007-83.png"}, {"slug": "126281rbr-0005", "url": "/rolex/datejust/126281rbr-0005", "collection": "Datejust 36 watches709", "title": "Rolex - 126281RBR-0005 Datejust 36 Stainless Steel / Everose / Diamond / White / Jubilee", "specs": {"Brand": "Rolex", "Family": "Datejust 36", "Reference": "126281RBR-0005", "Name": "Datejust 36 Stainless Steel / Everose / Diamond / White / Jubilee", "Movement": "Rolex caliber 3235 Hours, Minutes, Seconds | Date | Chronometer", "Produced": "2018", "Limited": "No", "Materials": "Rose Gold, Stainless Steel", "Bezel": "Gem-Set", "Glass": "Sapphire", "Back": "Closed", "Shape": "Round", "Diameter": "36.00 mm", "Lug Width": "20.00 mm", "W/R": "100.00 m", "Color": "White", "Indexes": "Stick / Dot", "Hands": "Stick"}, "image_url": "/watches/rolex/datejust/126281rbr-0005.jpg", "image_url_source": "https://cdn.watchbase.com/watch/lg/rolex/datejust/126281rbr-0005-de.png"}, {"slug": "126281rbr-0010", "url": "/rolex/datejust/126281rbr-0010", "collection": "Datejust 36 watches709", "title": "Rolex - 126281RBR-0010 Datejust 36 Stainless Steel / Everose / Diamond / MOP Diamond / Oyster", "specs": {"Brand": "Rolex", "Family": "Datejust 36", "Reference": "126281RBR-0010", "Name": "Datejust 36 Stainless Steel / Everose / Diamond / MOP Diamond / Oyster", "Movement": "Rolex caliber 3235 Hours, Minutes, Seconds | Date | Chronometer", "Produced": "2018", "Limited": "No", "Materials": "Rose Gold, Stainless Steel", "Bezel": "Gem-Set", "Glass": "Sapphire", "Back": "Closed", "Shape": "Round", "Diameter": "36.00 mm", "Lug Width": "20.00 mm", "W/R": "100.00 m", "Color": "White", "Material": "Mother of Pearl", "Finish": "Gloss", "Indexes": "Gem-Set Indexes", "Hands": "Stick"}, "image_url": "/watches/rolex/datejust/126281rbr-0010.jpg", "image_url_source": "https://cdn.watchbase.com/watch/lg/rolex/datejust/126281rbr-0010-ac.png"}, {"slug": "126281rbr-0003", "url": "/rolex/datejust/126281rbr-0003", "collection": "Datejust 36 watches709", "title": "Rolex - 126281RBR-0003 Datejust 36 Stainless Steel / Everose / Diamond / White Roman / Jubilee", "specs": {"Brand": "Rolex", "Family": "Datejust 36", "Reference": "126281RBR-0003", "Name": "Datejust 36 Stainless Steel / Everose / Diamond / White Roman / Jubilee", "Movement": "Rolex caliber 3235 Hours, Minutes, Seconds | Date | Chronometer", "Produced": "2018", "Limited": "No", "Materials": "Rose Gold, Stainless Steel", "Bezel": "Gem-Set", "Glass": "Sapphire", "Back": "Closed", "Shape": "Round", "Diameter": "36.00 mm", "Lug Width": "20.00 mm", "W/R": "100.00 m", "Color": "White", "Finish": "Gloss", "Indexes": "Roman Numerals", "Hands": "Stick"}, "image_url": "/watches/rolex/datejust/126281rbr-0003.jpg", "image_url_source": "https://cdn.watchbase.com/watch/lg/rolex/datejust/126281rbr-0003-e8.png"}, {"slug": "126281rbr-0006", "url": "/rolex/datejust/126281rbr-0006", "collection": "Datejust 36 watches709", "title": "Rolex - 126281RBR-0006 Datejust 36 Stainless Steel / Everose / Diamond / White / Oyster", "specs": {"Brand": "Rolex", "Family": "Datejust 36", "Reference": "126281RBR-0006", "Name": "Datejust 36 Stainless Steel / Everose / Diamond / White / Oyster", "Movement": "Rolex caliber 3235 Hours, Minutes, Seconds | Date | Chronometer", "Produced": "2018", "Limited": "No", "Materials": "Rose Gold, Stainless Steel", "Bezel": "Gem-Set", "Glass": "Sapphire", "Back": "Closed", "Shape": "Round", "Diameter": "36.00 mm", "Lug Width": "20.00 mm", "W/R": "100.00 m", "Color": "White", "Indexes": "Stick / Dot", "Hands": "Stick"}, "image_url": "/watches/rolex/datejust/126281rbr-0006.jpg", "image_url_source": "https://cdn.watchbase.com/watch/lg/rolex/datejust/126281rbr-0006-f3.png"}, {"slug": "126281rbr-0012", "url": "/rolex/datejust/126281rbr-0012", "collection": "Datejust 36 watches709", "title": "Rolex - 126281RBR-0012 Datejust 36 Stainless Steel / Everose / Diamond / Slate Roman Diamond / Oyster", "specs": {"Brand": "Rolex", "Family": "Datejust 36", "Reference": "126281RBR-0012", "Name": "Datejust 36 Stainless Steel / Everose / Diamond / Slate Roman Diamond / Oyster", "Movement": "Rolex caliber 3235 Hours, Minutes, Seconds | Date | Chronometer", "Produced": "2018", "Limited": "No", "Materials": "Rose Gold, Stainless Steel", "Bezel": "Gem-Set", "Glass": "Sapphire", "Back": "Closed", "Shape": "Round", "Diameter": "36.00 mm", "Lug Width": "20.00 mm", "W/R": "100.00 m", "Nickname": "Diamond 6-9 Dark Rhodium", "Color": "Grey", "Finish": "Sunburst", "Indexes": "Roman Numerals", "Hands": "Stick"}, "image_url": "/watches/rolex/datejust/126281rbr-0012.jpg", "image_url_source": "https://cdn.watchbase.com/watch/lg/rolex/datejust/126281rbr-0012-8f.png"}, {"slug": "126203-0016", "url": "/rolex/datejust/126203-0016", "collection": "Datejust 36 watches709", "title": "Rolex - 126203-0016 Datejust 36 Stainless Steel / Yellow Gold / Smooth / Champagne / Oyster", "specs": {"Brand": "Rolex", "Family": "Datejust 36", "Reference": "126203-0016", "Name": "Datejust 36 Stainless Steel / Yellow Gold / Smooth / Champagne / Oyster", "Movement": "Rolex caliber 3235 Hours, Minutes, Seconds | Date | Chronometer", "Produced": "2018", "Limited": "No", "Materials": "Yellow Gold, Stainless Steel", "Glass": "Sapphire", "Back": "Closed", "Shape": "Round", "Diameter": "36.00 mm", "Lug Width": "20.00 mm", "W/R": "100.00 m", "Color": "Champagne", "Indexes": "Stick / Dot", "Hands": "Stick"}, "image_url": "/watches/rolex/datejust/126203-0016.jpg", "image_url_source": "https://cdn.watchbase.com/watch/lg/rolex/datejust/126203-0016-22.png"}, {"slug": "126234-0025", "url": "/rolex/datejust/126234-0025", "collection": "Datejust 36 watches709", "title": "Rolex - 126234-0025 Datejust 36 Stainless Steel / Fluted / White Roman / Jubilee", "specs": {"Brand": "Rolex", "Family": "Datejust 36", "Reference": "126234-0025", "Name": "Datejust 36 Stainless Steel / Fluted / White Roman / Jubilee", "Movement": "Rolex caliber 3235 Hours, Minutes, Seconds | Date | Chronometer", "Produced": "2019", "Limited": "No", "Materials": "White Gold, Stainless Steel", "Glass": "Sapphire", "Back": "Closed", "Shape": "Round", "Diameter": "36.00 mm", "Lug Width": "20.00 mm", "W/R": "100.00 m", "Color": "White", "Finish": "Gloss", "Indexes": "Roman Numerals", "Hands": "Stick"}, "image_url": "/watches/rolex/datejust/126234-0025.jpg", "image_url_source": "https://cdn.watchbase.com/watch/lg/rolex/datejust/126234-0025-83.jpg"}, {"slug": "126234-0027", "url": "/rolex/datejust/126234-0027", "collection": "Datejust 36 watches709", "title": "Rolex - 126234-0027 Datejust 36 Stainless Steel / Fluted / Black-Diamond / Jubilee", "specs": {"Brand": "Rolex", "Family": "Datejust 36", "Reference": "126234-0027", "Name": "Datejust 36 Stainless Steel / Fluted / Black-Diamond / Jubilee", "Movement": "Rolex caliber 3235 Hours, Minutes, Seconds | Date | Chronometer", "Produced": "2019", "Limited": "No", "Materials": "White Gold, Stainless Steel", "Glass": "Sapphire", "Back": "Closed", "Shape": "Round", "Diameter": "36.00 mm", "Lug Width": "20.00 mm", "W/R": "100.00 m", "Color": "Black", "Finish": "Sunburst", "Indexes": "Gem-Set Indexes", "Hands": "Stick"}, "image_url": "/watches/rolex/datejust/126234-0027.jpg", "image_url_source": "https://cdn.watchbase.com/watch/lg/rolex/datejust/126234-0027-51.jpg"}, {"slug": "126234-0029", "url": "/rolex/datejust/126234-0029", "collection": "Datejust 36 watches709", "title": "Rolex - 126234-0029 Datejust 36 Stainless Steel / Fluted / Silver Roman-Diamonds / Jubilee", "specs": {"Brand": "Rolex", "Family": "Datejust 36", "Reference": "126234-0029", "Name": "Datejust 36 Stainless Steel / Fluted / Silver Roman-Diamonds / Jubilee", "Movement": "Rolex caliber 3235 Hours, Minutes, Seconds | Date | Chronometer", "Produced": "2019", "Limited": "No", "Materials": "White Gold, Stainless Steel", "Glass": "Sapphire", "Back": "Closed", "Shape": "Round", "Diameter": "36.00 mm", "Lug Width": "20.00 mm", "W/R": "100.00 m", "Color": "Silver", "Finish": "Sunburst", "Indexes": "Roman Numerals", "Hands": "Stick"}, "image_url": "/watches/rolex/datejust/126234-0029.jpg", "image_url_source": "https://cdn.watchbase.com/watch/lg/rolex/datejust/126234-0029-70.jpg"}, {"slug": "126234-0014", "url": "/rolex/datejust/126234-0014", "collection": "Datejust 36 watches709", "title": "Rolex - 126234-0014 Datejust 36 Stainless Steel / Fluted / Silver / Oyster", "specs": {"Brand": "Rolex", "Family": "Datejust 36", "Reference": "126234-0014", "Name": "Datejust 36 Stainless Steel / Fluted / Silver / Oyster", "Movement": "Rolex caliber 3235 Hours, Minutes, Seconds | Date | Chronometer", "Produced": "2019", "Limited": "No", "Materials": "White Gold, Stainless Steel", "Glass": "Sapphire", "Back": "Closed", "Shape": "Round", "Diameter": "36.00 mm", "Lug Width": "20.00 mm", "W/R": "100.00 m", "Color": "Silver", "Finish": "Sunburst", "Indexes": "Stick / Dot", "Hands": "Stick"}, "image_url": "/watches/rolex/datejust/126234-0014.jpg", "image_url_source": "https://cdn.watchbase.com/watch/lg/rolex/datejust/126234-0014-25.jpg"}, {"slug": "126234-0020", "url": "/rolex/datejust/126234-0020", "collection": "Datejust 36 watches709", "title": "Rolex - 126234-0020 Datejust 36 Stainless Steel / Fluted / MOP-Diamond / Oyster", "specs": {"Brand": "Rolex", "Family": "Datejust 36", "Reference": "126234-0020", "Name": "Datejust 36 Stainless Steel / Fluted / MOP-Diamond / Oyster", "Movement": "Rolex caliber 3235 Hours, Minutes, Seconds | Date | Chronometer", "Produced": "2019", "Limited": "No", "Materials": "White Gold, Stainless Steel", "Glass": "Sapphire", "Back": "Closed", "Shape": "Round", "Diameter": "36.00 mm", "Lug Width": "20.00 mm", "W/R": "100.00 m", "Color": "White", "Material": "Mother of Pearl", "Finish": "Gloss", "Indexes": "Gem-Set Indexes", "Hands": "Stick"}, "image_url": "/watches/rolex/datejust/126234-0020.jpg", "image_url_source": "https://cdn.watchbase.com/watch/lg/rolex/datejust/126234-0020-31.jpg"}, {"slug": "126234-0022", "url": "/rolex/datejust/126234-0022", "collection": "Datejust 36 watches709", "title": "Rolex - 126234-0022 Datejust 36 Stainless Steel / Fluted / Aubergine Roman-Diamonds / Oyster", "specs": {"Brand": "Rolex", "Family": "Datejust 36", "Reference": "126234-0022", "Name": "Datejust 36 Stainless Steel / Fluted / Aubergine Roman-Diamonds / Oyster", "Movement": "Rolex caliber 3235 Hours, Minutes, Seconds | Date | Chronometer", "Produced": "2019", "Limited": "No", "Materials": "White Gold, Stainless Steel", "Glass": "Sapphire", "Back": "Closed", "Shape": "Round", "Diameter": "36.00 mm", "Lug Width": "20.00 mm", "W/R": "100.00 m", "Color": "Purple", "Finish": "Sunburst", "Indexes": "Roman Numerals", "Hands": "Stick"}, "image_url": "/watches/rolex/datejust/126234-0022.jpg", "image_url_source": "https://cdn.watchbase.com/watch/lg/rolex/datejust/126234-0022-40.jpg"}, {"slug": "126234-0024", "url": "/rolex/datejust/126234-0024", "collection": "Datejust 36 watches709", "title": "Rolex - 126234-0024 Datejust 36 Stainless Steel / Fluted / Pink Jubilee / Oyster", "specs": {"Brand": "Rolex", "Family": "Datejust 36", "Reference": "126234-0024", "Name": "Datejust 36 Stainless Steel / Fluted / Pink Jubilee / Oyster", "Movement": "Rolex caliber 3235 Hours, Minutes, Seconds | Date | Chronometer", "Produced": "2019", "Limited": "No", "Materials": "White Gold, Stainless Steel", "Glass": "Sapphire", "Back": "Closed", "Shape": "Round", "Diameter": "36.00 mm", "Lug Width": "20.00 mm", "W/R": "100.00 m", "Nickname": "Jubilee", "Color": "Pink", "Finish": "Guilloche", "Indexes": "Gem-Set Indexes", "Hands": "Stick"}, "image_url": "/watches/rolex/datejust/126234-0024.jpg", "image_url_source": "https://cdn.watchbase.com/watch/lg/rolex/datejust/126234-0024-d5.jpg"}]}